{"match": {"video": "20190424 布达佩斯世乒赛 女单十六分之一决赛 孙颖莎vs伊藤美诚.mp4", "time": [2019, 4], "location": "", "type": "", "competition": 4, "round": 3}, "player": [[{"name": "孙颖莎", "country": "中国", "rank": "29", "rightHand": true, "isStraight": false, "face": [1, 1]}], [{"name": "伊藤美诚", "country": "日本", "rank": "7", "rightHand": true, "isStraight": false, "face": [2, 1]}]], "record": {"MatchNo": "20190424 布达佩斯世乒赛 女单十六分之一决赛 孙颖莎vs伊藤美诚", "result": [4, 1], "list": [{"GameNo": 1, "result": [11, 6], "score": [0, 0], "list": [{"RallyNo": 1, "startTime": 7.7295422, "endTime": 14.8913351, "startSide": 1, "winSide": 1, "score": [0, 0], "list": [{"StrikeNo": 1, "BallPosition": "S1", "StrikePosition": "S1", "StrikeTech": "Pendulum", "GameAction": "Serve", "StrikeEffect": "L4", "SpinKind": "ND", "HitPlayer": "10"}, {"StrikeNo": 2, "BallPosition": "BL", "StrikePosition": "B", "StrikeTech": "Topspin", "GameAction": "Receive", "StrikeEffect": "L3", "SpinKind": "ST", "HitPlayer": "00"}, {"StrikeNo": 3, "BallPosition": "BL", "StrikePosition": "B", "StrikeTech": "Attack", "GameAction": "Stalemate", "StrikeEffect": "L1", "SpinKind": "SK", "HitPlayer": "10"}, {"StrikeNo": 4, "BallPosition": "BL", "StrikePosition": "B", "StrikeTech": "Topspin", "GameAction": "Stalemate", "StrikeEffect": "L5", "SpinKind": "NT", "HitPlayer": "00"}]}, {"RallyNo": 2, "startTime": 21.6827601, "endTime": 30.0227614, "startSide": 1, "winSide": 0, "score": [0, 1], "list": [{"StrikeNo": 1, "BallPosition": "S1", "StrikePosition": "S1", "StrikeTech": "Reverse", "GameAction": "Serve", "StrikeEffect": "L2", "SpinKind": "ND", "HitPlayer": "10"}, {"StrikeNo": 2, "BallPosition": "MS", "StrikePosition": "B", "StrikeTech": "Short", "GameAction": "Receive", "StrikeEffect": "L4", "SpinKind": "ND", "HitPlayer": "00"}, {"StrikeNo": 3, "BallPosition": "BH", "StrikePosition": "B", "StrikeTech": "Topspin", "GameAction": "Offensive", "StrikeEffect": "L2", "SpinKind": "ST", "HitPlayer": "10"}, {"StrikeNo": 4, "BallPosition": "BL", "StrikePosition": "B", "StrikeTech": "Block", "GameAction": "Defensive", "StrikeEffect": "L4", "SpinKind": "NT", "HitPlayer": "00"}, {"StrikeNo": 5, "BallPosition": "BL", "StrikePosition": "B", "StrikeTech": "Attack", "GameAction": "Offensive", "StrikeEffect": "L3", "SpinKind": "SK", "HitPlayer": "10"}, {"StrikeNo": 6, "BallPosition": "BL", "StrikePosition": "B", "StrikeTech": "Topspin", "GameAction": "Stalemate", "StrikeEffect": "L1", "SpinKind": "NT", "HitPlayer": "00"}, {"StrikeNo": 7, "BallPosition": "ML", "StrikePosition": "B", "StrikeTech": "Block", "GameAction": "Defensive", "StrikeEffect": "L5", "SpinKind": "SK", "HitPlayer": "10"}]}, {"RallyNo": 3, "startTime": 39.9909291, "endTime": 45.8098467, "startSide": 0, "winSide": 0, "score": [1, 1], "list": [{"StrikeNo": 1, "BallPosition": "S1", "StrikePosition": "S1", "StrikeTech": "Pendulum", "GameAction": "Serve", "StrikeEffect": "L1", "SpinKind": "ND", "HitPlayer": "00"}, {"StrikeNo": 2, "BallPosition": "BH", "StrikePosition": "B", "StrikeTech": "Flick", "GameAction": "Receive", "StrikeEffect": "L5", "SpinKind": "SK", "HitPlayer": "10"}]}, {"RallyNo": 4, "startTime": 54.0419302, "endTime": 59.946314, "startSide": 0, "winSide": 0, "score": [2, 1], "list": [{"StrikeNo": 1, "BallPosition": "S1", "StrikePosition": "S1", "StrikeTech": "Pendulum", "GameAction": "Serve", "StrikeEffect": "L1", "SpinKind": "NT", "HitPlayer": "00"}, {"StrikeNo": 2, "BallPosition": "BS", "StrikePosition": "B", "StrikeTech": "Flick", "GameAction": "Receive", "StrikeEffect": "L5", "SpinKind": "SK", "HitPlayer": "10"}]}, {"RallyNo": 5, "startTime": 78.1815242, "endTime": 87.6453799, "startSide": 1, "winSide": 0, "score": [3, 1], "list": [{"StrikeNo": 1, "BallPosition": "S2", "StrikePosition": "S2", "StrikeTech": "Reverse", "GameAction": "Serve", "StrikeEffect": "L4", "SpinKind": "ND", "HitPlayer": "10"}, {"StrikeNo": 2, "BallPosition": "FH", "StrikePosition": "F", "StrikeTech": "Topspin", "GameAction": "Receive", "StrikeEffect": "L3", "SpinKind": "ST", "HitPlayer": "00"}, {"StrikeNo": 3, "BallPosition": "ML", "StrikePosition": "B", "StrikeTech": "Attack", "GameAction": "Stalemate", "StrikeEffect": "L3", "SpinKind": "SK", "HitPlayer": "10"}, {"StrikeNo": 4, "BallPosition": "BL", "StrikePosition": "B", "StrikeTech": "Topspin", "GameAction": "Stalemate", "StrikeEffect": "L2", "SpinKind": "NT", "HitPlayer": "00"}, {"StrikeNo": 5, "BallPosition": "FL", "StrikePosition": "F", "StrikeTech": "Block", "GameAction": "Defensive", "StrikeEffect": "L4", "SpinKind": "NT", "HitPlayer": "10"}, {"StrikeNo": 6, "BallPosition": "FL", "StrikePosition": "F", "StrikeTech": "Smash", "GameAction": "Offensive", "StrikeEffect": "L1", "SpinKind": "NT", "HitPlayer": "00"}, {"StrikeNo": 7, "BallPosition": "FL", "StrikePosition": "F", "StrikeTech": "Attack", "GameAction": "Stalemate", "StrikeEffect": "L5", "SpinKind": "NT", "HitPlayer": "10"}]}, {"RallyNo": 6, "startTime": 97.9564301, "endTime": 104.9968557, "startSide": 1, "winSide": 1, "score": [4, 1], "list": [{"StrikeNo": 1, "BallPosition": "S2", "StrikePosition": "S2", "StrikeTech": "Pendulum", "GameAction": "Serve", "StrikeEffect": "L2", "SpinKind": "ND", "HitPlayer": "10"}, {"StrikeNo": 2, "BallPosition": "FS", "StrikePosition": "F", "StrikeTech": "Push", "GameAction": "Receive", "StrikeEffect": "L4", "SpinKind": "ND", "HitPlayer": "00"}, {"StrikeNo": 3, "BallPosition": "FL", "StrikePosition": "F", "StrikeTech": "Topspin", "GameAction": "Offensive", "StrikeEffect": "L1", "SpinKind": "ST", "HitPlayer": "10"}, {"StrikeNo": 4, "BallPosition": "BL", "StrikePosition": "B", "StrikeTech": "Block", "GameAction": "Defensive", "StrikeEffect": "L5", "SpinKind": "NT", "HitPlayer": "00"}]}, {"RallyNo": 7, "startTime": 116.5899396, "endTime": 124.1610528, "startSide": 0, "winSide": 0, "score": [4, 2], "list": [{"StrikeNo": 1, "BallPosition": "S1", "StrikePosition": "S1", "StrikeTech": "Pendulum", "GameAction": "Serve", "StrikeEffect": "L4", "SpinKind": "NT", "HitPlayer": "00"}, {"StrikeNo": 2, "BallPosition": "ML", "StrikePosition": "B", "StrikeTech": "Attack", "GameAction": "Receive", "StrikeEffect": "L3", "SpinKind": "SK", "HitPlayer": "10"}, {"StrikeNo": 3, "BallPosition": "BL", "StrikePosition": "B", "StrikeTech": "Topspin", "GameAction": "Stalemate", "StrikeEffect": "L1", "SpinKind": "NT", "HitPlayer": "00"}, {"StrikeNo": 4, "BallPosition": "BL", "StrikePosition": "B", "StrikeTech": "Block", "GameAction": "Defensive", "StrikeEffect": "L5", "SpinKind": "SK", "HitPlayer": "10"}]}, {"RallyNo": 8, "startTime": 132.659574, "endTime": 143.2000706, "startSide": 0, "winSide": 0, "score": [5, 2], "list": [{"StrikeNo": 1, "BallPosition": "S1", "StrikePosition": "S1", "StrikeTech": "Pendulum", "GameAction": "Serve", "StrikeEffect": "L4", "SpinKind": "NT", "HitPlayer": "00"}, {"StrikeNo": 2, "BallPosition": "BL", "StrikePosition": "B", "StrikeTech": "Attack", "GameAction": "Receive", "StrikeEffect": "L3", "SpinKind": "SK", "HitPlayer": "10"}, {"StrikeNo": 3, "BallPosition": "BL", "StrikePosition": "B", "StrikeTech": "Topspin", "GameAction": "Stalemate", "StrikeEffect": "L3", "SpinKind": "NT", "HitPlayer": "00"}, {"StrikeNo": 4, "BallPosition": "BL", "StrikePosition": "B", "StrikeTech": "Attack", "GameAction": "Stalemate", "StrikeEffect": "L3", "SpinKind": "SK", "HitPlayer": "10"}, {"StrikeNo": 5, "BallPosition": "BL", "StrikePosition": "B", "StrikeTech": "Topspin", "GameAction": "Stalemate", "StrikeEffect": "L3", "SpinKind": "NT", "HitPlayer": "00"}, {"StrikeNo": 6, "BallPosition": "BL", "StrikePosition": "B", "StrikeTech": "Attack", "GameAction": "Stalemate", "StrikeEffect": "L3", "SpinKind": "SK", "HitPlayer": "10"}, {"StrikeNo": 7, "BallPosition": "ML", "StrikePosition": "B", "StrikeTech": "Topspin", "GameAction": "Stalemate", "StrikeEffect": "L3", "SpinKind": "NT", "HitPlayer": "00"}, {"StrikeNo": 8, "BallPosition": "BL", "StrikePosition": "B", "StrikeTech": "Attack", "GameAction": "Stalemate", "StrikeEffect": "L3", "SpinKind": "SK", "HitPlayer": "10"}, {"StrikeNo": 9, "BallPosition": "ML", "StrikePosition": "F", "StrikeTech": "Topspin", "GameAction": "Stalemate", "StrikeEffect": "L2", "SpinKind": "NT", "HitPlayer": "00"}, {"StrikeNo": 10, "BallPosition": "FL", "StrikePosition": "F", "StrikeTech": "Block", "GameAction": "Defensive", "StrikeEffect": "L4", "SpinKind": "NT", "HitPlayer": "10"}, {"StrikeNo": 11, "BallPosition": "BL", "StrikePosition": "P", "StrikeTech": "Smash", "GameAction": "Offensive", "StrikeEffect": "L1", "SpinKind": "NT", "HitPlayer": "00"}, {"StrikeNo": 12, "BallPosition": "FL", "StrikePosition": "F", "StrikeTech": "Lob", "GameAction": "Defensive", "StrikeEffect": "L5", "SpinKind": "WT", "HitPlayer": "10"}]}, {"RallyNo": 9, "startTime": 154.8189544, "endTime": 164.1632267, "startSide": 1, "winSide": 0, "score": [6, 2], "list": [{"StrikeNo": 1, "BallPosition": "S1", "StrikePosition": "S1", "StrikeTech": "Pendulum", "GameAction": "Serve", "StrikeEffect": "L3", "SpinKind": "ND", "HitPlayer": "10"}, {"StrikeNo": 2, "BallPosition": "BS", "StrikePosition": "B", "StrikeTech": "Short", "GameAction": "Receive", "StrikeEffect": "L3", "SpinKind": "ND", "HitPlayer": "00"}, {"StrikeNo": 3, "BallPosition": "MS", "StrikePosition": "B", "StrikeTech": "Short", "GameAction": "Controlled", "StrikeEffect": "L3", "SpinKind": "ND", "HitPlayer": "10"}, {"StrikeNo": 4, "BallPosition": "MS", "StrikePosition": "B", "StrikeTech": "Push", "GameAction": "Controlled", "StrikeEffect": "L1", "SpinKind": "ND", "HitPlayer": "00"}, {"StrikeNo": 5, "BallPosition": "BL", "StrikePosition": "B", "StrikeTech": "Topspin", "GameAction": "Offensive", "StrikeEffect": "L5", "SpinKind": "ST", "HitPlayer": "10"}]}, {"RallyNo": 10, "startTime": 173.6878522, "endTime": 183.1357079, "startSide": 1, "winSide": 1, "score": [7, 2], "list": [{"StrikeNo": 1, "BallPosition": "S1", "StrikePosition": "S1", "StrikeTech": "Pendulum", "GameAction": "Serve", "StrikeEffect": "L4", "SpinKind": "NT", "HitPlayer": "10"}, {"StrikeNo": 2, "BallPosition": "BL", "StrikePosition": "B", "StrikeTech": "Topspin", "GameAction": "Receive", "StrikeEffect": "L2", "SpinKind": "NT", "HitPlayer": "00"}, {"StrikeNo": 3, "BallPosition": "BL", "StrikePosition": "B", "StrikeTech": "Block", "GameAction": "Defensive", "StrikeEffect": "L4", "SpinKind": "SK", "HitPlayer": "10"}, {"StrikeNo": 4, "BallPosition": "SP", "StrikePosition": "F", "StrikeTech": "Topspin", "GameAction": "Offensive", "StrikeEffect": "L2", "SpinKind": "NT", "HitPlayer": "00"}, {"StrikeNo": 5, "BallPosition": "FL", "StrikePosition": "F", "StrikeTech": "Block", "GameAction": "Defensive", "StrikeEffect": "L4", "SpinKind": "NT", "HitPlayer": "10"}, {"StrikeNo": 6, "BallPosition": "FL", "StrikePosition": "F", "StrikeTech": "Topspin", "GameAction": "Offensive", "StrikeEffect": "L3", "SpinKind": "NT", "HitPlayer": "00"}, {"StrikeNo": 7, "BallPosition": "FL", "StrikePosition": "F", "StrikeTech": "Attack", "GameAction": "Stalemate", "StrikeEffect": "L2", "SpinKind": "NT", "HitPlayer": "10"}, {"StrikeNo": 8, "BallPosition": "BL", "StrikePosition": "B", "StrikeTech": "Block", "GameAction": "Defensive", "StrikeEffect": "L2", "SpinKind": "NT", "HitPlayer": "00"}, {"StrikeNo": 9, "BallPosition": "ML", "StrikePosition": "B", "StrikeTech": "Others", "GameAction": "Defensive", "StrikeEffect": "L1", "SpinKind": "NT", "HitPlayer": "10"}, {"StrikeNo": 10, "BallPosition": "ML", "StrikePosition": "F", "StrikeTech": "Topspin", "GameAction": "Offensive", "StrikeEffect": "L5", "SpinKind": "ST", "HitPlayer": "00"}]}, {"RallyNo": 11, "startTime": 210.7521885, "endTime": 217.2979395, "startSide": 0, "winSide": 0, "score": [7, 3], "list": [{"StrikeNo": 1, "BallPosition": "S1", "StrikePosition": "S1", "StrikeTech": "Pendulum", "GameAction": "Serve", "StrikeEffect": "L4", "SpinKind": "NT", "HitPlayer": "00"}, {"StrikeNo": 2, "BallPosition": "ML", "StrikePosition": "B", "StrikeTech": "Attack", "GameAction": "Receive", "StrikeEffect": "L3", "SpinKind": "SK", "HitPlayer": "10"}, {"StrikeNo": 3, "BallPosition": "FL", "StrikePosition": "F", "StrikeTech": "Topspin", "GameAction": "Stalemate", "StrikeEffect": "L1", "SpinKind": "NT", "HitPlayer": "00"}, {"StrikeNo": 4, "BallPosition": "BL", "StrikePosition": "B", "StrikeTech": "Block", "GameAction": "Defensive", "StrikeEffect": "L5", "SpinKind": "SK", "HitPlayer": "10"}]}, {"RallyNo": 12, "startTime": 231.7072314, "endTime": 237.9397741, "startSide": 0, "winSide": 1, "score": [8, 3], "list": [{"StrikeNo": 1, "BallPosition": "S1", "StrikePosition": "S1", "StrikeTech": "Pendulum", "GameAction": "Serve", "StrikeEffect": "L4", "SpinKind": "NT", "HitPlayer": "00"}, {"StrikeNo": 2, "BallPosition": "MS", "StrikePosition": "B", "StrikeTech": "Flick", "GameAction": "Receive", "StrikeEffect": "L1", "SpinKind": "SK", "HitPlayer": "10"}, {"StrikeNo": 3, "BallPosition": "BL", "StrikePosition": "B", "StrikeTech": "Topspin", "GameAction": "Stalemate", "StrikeEffect": "L5", "SpinKind": "NT", "HitPlayer": "00"}]}, {"RallyNo": 13, "startTime": 255.1171708, "endTime": 263.692818, "startSide": 1, "winSide": 1, "score": [8, 4], "list": [{"StrikeNo": 1, "BallPosition": "S1", "StrikePosition": "S1", "StrikeTech": "Pendulum", "GameAction": "Serve", "StrikeEffect": "L2", "SpinKind": "ND", "HitPlayer": "10"}, {"StrikeNo": 2, "BallPosition": "MS", "StrikePosition": "B", "StrikeTech": "Push", "GameAction": "Receive", "StrikeEffect": "L4", "SpinKind": "ND", "HitPlayer": "00"}, {"StrikeNo": 3, "BallPosition": "BL", "StrikePosition": "B", "StrikeTech": "Topspin", "GameAction": "Offensive", "StrikeEffect": "L3", "SpinKind": "ST", "HitPlayer": "10"}, {"StrikeNo": 4, "BallPosition": "BL", "StrikePosition": "B", "StrikeTech": "Topspin", "GameAction": "Stalemate", "StrikeEffect": "L3", "SpinKind": "NT", "HitPlayer": "00"}, {"StrikeNo": 5, "BallPosition": "BL", "StrikePosition": "B", "StrikeTech": "Attack", "GameAction": "Stalemate", "StrikeEffect": "L1", "SpinKind": "SK", "HitPlayer": "10"}, {"StrikeNo": 6, "BallPosition": "FL", "StrikePosition": "F", "StrikeTech": "Block", "GameAction": "Defensive", "StrikeEffect": "L5", "SpinKind": "WT", "HitPlayer": "00"}]}, {"RallyNo": 14, "startTime": 275.1046731, "endTime": 284.0467657, "startSide": 1, "winSide": 1, "score": [8, 5], "list": [{"StrikeNo": 1, "BallPosition": "S1", "StrikePosition": "S1", "StrikeTech": "Reverse", "GameAction": "Serve", "StrikeEffect": "L4", "SpinKind": "NT", "HitPlayer": "10"}, {"StrikeNo": 2, "BallPosition": "BL", "StrikePosition": "B", "StrikeTech": "Topspin", "GameAction": "Receive", "StrikeEffect": "L3", "SpinKind": "NT", "HitPlayer": "00"}, {"StrikeNo": 3, "BallPosition": "BL", "StrikePosition": "B", "StrikeTech": "Attack", "GameAction": "Stalemate", "StrikeEffect": "L3", "SpinKind": "SK", "HitPlayer": "10"}, {"StrikeNo": 4, "BallPosition": "BL", "StrikePosition": "B", "StrikeTech": "Topspin", "GameAction": "Stalemate", "StrikeEffect": "L3", "SpinKind": "NT", "HitPlayer": "00"}, {"StrikeNo": 5, "BallPosition": "BL", "StrikePosition": "B", "StrikeTech": "Attack", "GameAction": "Stalemate", "StrikeEffect": "L3", "SpinKind": "SK", "HitPlayer": "10"}, {"StrikeNo": 6, "BallPosition": "ML", "StrikePosition": "F", "StrikeTech": "Topspin", "GameAction": "Stalemate", "StrikeEffect": "L2", "SpinKind": "NT", "HitPlayer": "00"}, {"StrikeNo": 7, "BallPosition": "FL", "StrikePosition": "F", "StrikeTech": "Block", "GameAction": "Defensive", "StrikeEffect": "L1", "SpinKind": "NT", "HitPlayer": "10"}, {"StrikeNo": 8, "BallPosition": "FL", "StrikePosition": "F", "StrikeTech": "Topspin", "GameAction": "Offensive", "StrikeEffect": "L5", "SpinKind": "NT", "HitPlayer": "00"}]}, {"RallyNo": 15, "startTime": 302.3250996, "endTime": 309.8227257, "startSide": 0, "winSide": 0, "score": [8, 6], "list": [{"StrikeNo": 1, "BallPosition": "S1", "StrikePosition": "S1", "StrikeTech": "Pendulum", "GameAction": "Serve", "StrikeEffect": "L4", "SpinKind": "NT", "HitPlayer": "00"}, {"StrikeNo": 2, "BallPosition": "ML", "StrikePosition": "B", "StrikeTech": "Attack", "GameAction": "Receive", "StrikeEffect": "L3", "SpinKind": "SK", "HitPlayer": "10"}, {"StrikeNo": 3, "BallPosition": "BL", "StrikePosition": "B", "StrikeTech": "Topspin", "GameAction": "Stalemate", "StrikeEffect": "L3", "SpinKind": "NT", "HitPlayer": "00"}, {"StrikeNo": 4, "BallPosition": "BL", "StrikePosition": "B", "StrikeTech": "Attack", "GameAction": "Stalemate", "StrikeEffect": "L3", "SpinKind": "SK", "HitPlayer": "10"}, {"StrikeNo": 5, "BallPosition": "FL", "StrikePosition": "F", "StrikeTech": "Topspin", "GameAction": "Stalemate", "StrikeEffect": "L1", "SpinKind": "NT", "HitPlayer": "00"}, {"StrikeNo": 6, "BallPosition": "BL", "StrikePosition": "B", "StrikeTech": "Block", "GameAction": "Defensive", "StrikeEffect": "L5", "SpinKind": "WT", "HitPlayer": "10"}]}, {"RallyNo": 16, "startTime": 327.0959351, "endTime": 335.6178402, "startSide": 0, "winSide": 0, "score": [9, 6], "list": [{"StrikeNo": 1, "BallPosition": "S1", "StrikePosition": "S1", "StrikeTech": "Pendulum", "GameAction": "Serve", "StrikeEffect": "L4", "SpinKind": "NT", "HitPlayer": "00"}, {"StrikeNo": 2, "BallPosition": "ML", "StrikePosition": "P", "StrikeTech": "Topspin", "GameAction": "Receive", "StrikeEffect": "L3", "SpinKind": "NT", "HitPlayer": "10"}, {"StrikeNo": 3, "BallPosition": "BL", "StrikePosition": "B", "StrikeTech": "Topspin", "GameAction": "Stalemate", "StrikeEffect": "L3", "SpinKind": "NT", "HitPlayer": "00"}, {"StrikeNo": 4, "BallPosition": "BL", "StrikePosition": "B", "StrikeTech": "Attack", "GameAction": "Stalemate", "StrikeEffect": "L3", "SpinKind": "SK", "HitPlayer": "10"}, {"StrikeNo": 5, "BallPosition": "BL", "StrikePosition": "B", "StrikeTech": "Topspin", "GameAction": "Stalemate", "StrikeEffect": "L1", "SpinKind": "NT", "HitPlayer": "00"}, {"StrikeNo": 6, "BallPosition": "BL", "StrikePosition": "B", "StrikeTech": "Block", "GameAction": "Defensive", "StrikeEffect": "L5", "SpinKind": "SK", "HitPlayer": "10"}]}, {"RallyNo": 17, "startTime": 349.4612368, "endTime": 354.6398913, "startSide": 1, "winSide": 0, "score": [10, 6], "list": [{"StrikeNo": 1, "BallPosition": "S1", "StrikePosition": "S1", "StrikeTech": "Pendulum", "GameAction": "Serve", "StrikeEffect": "L3", "SpinKind": "ND", "HitPlayer": "10"}, {"StrikeNo": 2, "BallPosition": "BS", "StrikePosition": "B", "StrikeTech": "Short", "GameAction": "Receive", "StrikeEffect": "L3", "SpinKind": "ND", "HitPlayer": "00"}, {"StrikeNo": 3, "BallPosition": "FS", "StrikePosition": "F", "StrikeTech": "Short", "GameAction": "Controlled", "StrikeEffect": "L3", "SpinKind": "ND", "HitPlayer": "10"}, {"StrikeNo": 4, "BallPosition": "FS", "StrikePosition": "F", "StrikeTech": "Push", "GameAction": "Controlled", "StrikeEffect": "L1", "SpinKind": "ND", "HitPlayer": "00"}, {"StrikeNo": 5, "BallPosition": "BL", "StrikePosition": "B", "StrikeTech": "Topspin", "GameAction": "Offensive", "StrikeEffect": "L5", "SpinKind": "ST", "HitPlayer": "10"}]}]}, {"GameNo": 2, "result": [11, 9], "score": [1, 0], "list": [{"RallyNo": 1, "startTime": 447.6062046, "endTime": 455.18781, "startSide": 0, "winSide": 1, "score": [0, 0], "list": [{"StrikeNo": 1, "BallPosition": "S1", "StrikePosition": "S1", "StrikeTech": "Pendulum", "GameAction": "Serve", "StrikeEffect": "L4", "SpinKind": "NT", "HitPlayer": "00"}, {"StrikeNo": 2, "BallPosition": "ML", "StrikePosition": "B", "StrikeTech": "Attack", "GameAction": "Receive", "StrikeEffect": "L3", "SpinKind": "SK", "HitPlayer": "10"}, {"StrikeNo": 3, "BallPosition": "ML", "StrikePosition": "B", "StrikeTech": "Topspin", "GameAction": "Stalemate", "StrikeEffect": "L3", "SpinKind": "NT", "HitPlayer": "00"}, {"StrikeNo": 4, "BallPosition": "BL", "StrikePosition": "B", "StrikeTech": "Attack", "GameAction": "Stalemate", "StrikeEffect": "L1", "SpinKind": "SK", "HitPlayer": "10"}, {"StrikeNo": 5, "BallPosition": "BL", "StrikePosition": "B", "StrikeTech": "Block", "GameAction": "Defensive", "StrikeEffect": "L5", "SpinKind": "WT", "HitPlayer": "00"}]}, {"RallyNo": 2, "startTime": 465.7958526, "endTime": 473.2600204, "startSide": 0, "winSide": 1, "score": [0, 1], "list": [{"StrikeNo": 1, "BallPosition": "S1", "StrikePosition": "S1", "StrikeTech": "Pendulum", "GameAction": "Serve", "StrikeEffect": "L3", "SpinKind": "ND", "HitPlayer": "00"}, {"StrikeNo": 2, "BallPosition": "FS", "StrikePosition": "T", "StrikeTech": "Short", "GameAction": "Receive", "StrikeEffect": "L3", "SpinKind": "ND", "HitPlayer": "10"}, {"StrikeNo": 3, "BallPosition": "FS", "StrikePosition": "F", "StrikeTech": "Push", "GameAction": "Controlled", "StrikeEffect": "L4", "SpinKind": "ND", "HitPlayer": "00"}, {"StrikeNo": 4, "BallPosition": "FL", "StrikePosition": "F", "StrikeTech": "Topspin", "GameAction": "Offensive", "StrikeEffect": "L1", "SpinKind": "ST", "HitPlayer": "10"}, {"StrikeNo": 5, "BallPosition": "BL", "StrikePosition": "B", "StrikeTech": "Block", "GameAction": "Defensive", "StrikeEffect": "L5", "SpinKind": "NT", "HitPlayer": "00"}]}, {"RallyNo": 3, "startTime": 482.6289871, "endTime": 490.8090171, "startSide": 1, "winSide": 0, "score": [0, 2], "list": [{"StrikeNo": 1, "BallPosition": "S1", "StrikePosition": "S1", "StrikeTech": "Reverse", "GameAction": "Serve", "StrikeEffect": "L2", "SpinKind": "ND", "HitPlayer": "10"}, {"StrikeNo": 2, "BallPosition": "BS", "StrikePosition": "B", "StrikeTech": "Push", "GameAction": "Receive", "StrikeEffect": "L4", "SpinKind": "ND", "HitPlayer": "00"}, {"StrikeNo": 3, "BallPosition": "BL", "StrikePosition": "B", "StrikeTech": "Topspin", "GameAction": "Offensive", "StrikeEffect": "L3", "SpinKind": "ST", "HitPlayer": "10"}, {"StrikeNo": 4, "BallPosition": "BL", "StrikePosition": "B", "StrikeTech": "Topspin", "GameAction": "Stalemate", "StrikeEffect": "L3", "SpinKind": "NT", "HitPlayer": "00"}, {"StrikeNo": 5, "BallPosition": "BL", "StrikePosition": "B", "StrikeTech": "Attack", "GameAction": "Stalemate", "StrikeEffect": "L3", "SpinKind": "SK", "HitPlayer": "10"}, {"StrikeNo": 6, "BallPosition": "BL", "StrikePosition": "B", "StrikeTech": "Topspin", "GameAction": "Stalemate", "StrikeEffect": "L1", "SpinKind": "NT", "HitPlayer": "00"}, {"StrikeNo": 7, "BallPosition": "BL", "StrikePosition": "B", "StrikeTech": "Attack", "GameAction": "Stalemate", "StrikeEffect": "L5", "SpinKind": "SK", "HitPlayer": "10"}]}, {"RallyNo": 4, "startTime": 500.4803927, "endTime": 506.6157687, "startSide": 1, "winSide": 1, "score": [1, 2], "list": [{"StrikeNo": 1, "BallPosition": "S1", "StrikePosition": "S1", "StrikeTech": "Reverse", "GameAction": "Serve", "StrikeEffect": "L4", "SpinKind": "NT", "HitPlayer": "10"}, {"StrikeNo": 2, "BallPosition": "BL", "StrikePosition": "B", "StrikeTech": "Topspin", "GameAction": "Receive", "StrikeEffect": "L3", "SpinKind": "NT", "HitPlayer": "00"}, {"StrikeNo": 3, "BallPosition": "BL", "StrikePosition": "B", "StrikeTech": "Attack", "GameAction": "Stalemate", "StrikeEffect": "L1", "SpinKind": "SK", "HitPlayer": "10"}, {"StrikeNo": 4, "BallPosition": "BL", "StrikePosition": "B", "StrikeTech": "Topspin", "GameAction": "Stalemate", "StrikeEffect": "L5", "SpinKind": "NT", "HitPlayer": "00"}]}, {"RallyNo": 5, "startTime": 532.2374572, "endTime": 539.9626251, "startSide": 0, "winSide": 1, "score": [1, 3], "list": [{"StrikeNo": 1, "BallPosition": "S1", "StrikePosition": "S1", "StrikeTech": "Pendulum", "GameAction": "Serve", "StrikeEffect": "L4", "SpinKind": "NT", "HitPlayer": "00"}, {"StrikeNo": 2, "BallPosition": "BS", "StrikePosition": "B", "StrikeTech": "Flick", "GameAction": "Receive", "StrikeEffect": "L3", "SpinKind": "SK", "HitPlayer": "10"}, {"StrikeNo": 3, "BallPosition": "BL", "StrikePosition": "B", "StrikeTech": "Topspin", "GameAction": "Stalemate", "StrikeEffect": "L2", "SpinKind": "NT", "HitPlayer": "00"}, {"StrikeNo": 4, "BallPosition": "BL", "StrikePosition": "B", "StrikeTech": "Block", "GameAction": "Defensive", "StrikeEffect": "L1", "SpinKind": "SK", "HitPlayer": "10"}, {"StrikeNo": 5, "BallPosition": "BL", "StrikePosition": "B", "StrikeTech": "Topspin", "GameAction": "Offensive", "StrikeEffect": "L5", "SpinKind": "WT", "HitPlayer": "00"}]}, {"RallyNo": 6, "startTime": 552.0179173, "endTime": 560.5089187, "startSide": 0, "winSide": 0, "score": [1, 4], "list": [{"StrikeNo": 1, "BallPosition": "S1", "StrikePosition": "S1", "StrikeTech": "Pendulum", "GameAction": "Serve", "StrikeEffect": "L2", "SpinKind": "NT", "HitPlayer": "00"}, {"StrikeNo": 2, "BallPosition": "ML", "StrikePosition": "B", "StrikeTech": "Push", "GameAction": "Receive", "StrikeEffect": "L4", "SpinKind": "ND", "HitPlayer": "10"}, {"StrikeNo": 3, "BallPosition": "ML", "StrikePosition": "F", "StrikeTech": "Topspin", "GameAction": "Offensive", "StrikeEffect": "L1", "SpinKind": "ST", "HitPlayer": "00"}, {"StrikeNo": 4, "BallPosition": "FL", "StrikePosition": "F", "StrikeTech": "Block", "GameAction": "Defensive", "StrikeEffect": "L5", "SpinKind": "NT", "HitPlayer": "10"}]}, {"RallyNo": 7, "startTime": 574.0271692, "endTime": 581.3573578, "startSide": 1, "winSide": 0, "score": [2, 4], "list": [{"StrikeNo": 1, "BallPosition": "S1", "StrikePosition": "S1", "StrikeTech": "Reverse", "GameAction": "Serve", "StrikeEffect": "L4", "SpinKind": "NT", "HitPlayer": "10"}, {"StrikeNo": 2, "BallPosition": "FS", "StrikePosition": "T", "StrikeTech": "Flick", "GameAction": "Receive", "StrikeEffect": "L3", "SpinKind": "NT", "HitPlayer": "00"}, {"StrikeNo": 3, "BallPosition": "BL", "StrikePosition": "B", "StrikeTech": "Attack", "GameAction": "Stalemate", "StrikeEffect": "L3", "SpinKind": "SK", "HitPlayer": "10"}, {"StrikeNo": 4, "BallPosition": "BL", "StrikePosition": "B", "StrikeTech": "Topspin", "GameAction": "Stalemate", "StrikeEffect": "L1", "SpinKind": "NT", "HitPlayer": "00"}, {"StrikeNo": 5, "BallPosition": "BL", "StrikePosition": "B", "StrikeTech": "Attack", "GameAction": "Stalemate", "StrikeEffect": "L5", "SpinKind": "SK", "HitPlayer": "10"}]}, {"RallyNo": 8, "startTime": 592.5821294, "endTime": 597.7136797, "startSide": 1, "winSide": 0, "score": [3, 4], "list": [{"StrikeNo": 1, "BallPosition": "S1", "StrikePosition": "S1", "StrikeTech": "Reverse", "GameAction": "Serve", "StrikeEffect": "L5", "SpinKind": "NT", "HitPlayer": "10"}]}, {"RallyNo": 9, "startTime": 609.9693475, "endTime": 617.385419, "startSide": 0, "winSide": 1, "score": [4, 4], "list": [{"StrikeNo": 1, "BallPosition": "S1", "StrikePosition": "S1", "StrikeTech": "Pendulum", "GameAction": "Serve", "StrikeEffect": "L4", "SpinKind": "NT", "HitPlayer": "00"}, {"StrikeNo": 2, "BallPosition": "ML", "StrikePosition": "B", "StrikeTech": "Attack", "GameAction": "Receive", "StrikeEffect": "L1", "SpinKind": "SK", "HitPlayer": "10"}, {"StrikeNo": 3, "BallPosition": "FL", "StrikePosition": "F", "StrikeTech": "Topspin", "GameAction": "Stalemate", "StrikeEffect": "L5", "SpinKind": "NT", "HitPlayer": "00"}]}, {"RallyNo": 10, "startTime": 634.1668781, "endTime": 640.3240458, "startSide": 0, "winSide": 0, "score": [4, 5], "list": [{"StrikeNo": 1, "BallPosition": "S1", "StrikePosition": "S1", "StrikeTech": "Pendulum", "GameAction": "Serve", "StrikeEffect": "L4", "SpinKind": "NT", "HitPlayer": "00"}, {"StrikeNo": 2, "BallPosition": "BL", "StrikePosition": "B", "StrikeTech": "Attack", "GameAction": "Receive", "StrikeEffect": "L3", "SpinKind": "SK", "HitPlayer": "10"}, {"StrikeNo": 3, "BallPosition": "BL", "StrikePosition": "B", "StrikeTech": "Topspin", "GameAction": "Stalemate", "StrikeEffect": "L3", "SpinKind": "NT", "HitPlayer": "00"}, {"StrikeNo": 4, "BallPosition": "BL", "StrikePosition": "B", "StrikeTech": "Attack", "GameAction": "Stalemate", "StrikeEffect": "L3", "SpinKind": "SK", "HitPlayer": "10"}, {"StrikeNo": 5, "BallPosition": "BL", "StrikePosition": "B", "StrikeTech": "Topspin", "GameAction": "Stalemate", "StrikeEffect": "L1", "SpinKind": "NT", "HitPlayer": "00"}, {"StrikeNo": 6, "BallPosition": "BL", "StrikePosition": "B", "StrikeTech": "Attack", "GameAction": "Stalemate", "StrikeEffect": "L5", "SpinKind": "SK", "HitPlayer": "10"}]}, {"RallyNo": 11, "startTime": 652.7267964, "endTime": 659.3461724, "startSide": 1, "winSide": 1, "score": [5, 5], "list": [{"StrikeNo": 1, "BallPosition": "S1", "StrikePosition": "S1", "StrikeTech": "Reverse", "GameAction": "Serve", "StrikeEffect": "L4", "SpinKind": "ND", "HitPlayer": "10"}, {"StrikeNo": 2, "BallPosition": "BL", "StrikePosition": "B", "StrikeTech": "Topspin", "GameAction": "Receive", "StrikeEffect": "L3", "SpinKind": "ST", "HitPlayer": "00"}, {"StrikeNo": 3, "BallPosition": "ML", "StrikePosition": "B", "StrikeTech": "Attack", "GameAction": "Stalemate", "StrikeEffect": "L1", "SpinKind": "SK", "HitPlayer": "10"}, {"StrikeNo": 4, "BallPosition": "FL", "StrikePosition": "F", "StrikeTech": "Topspin", "GameAction": "Stalemate", "StrikeEffect": "L5", "SpinKind": "NT", "HitPlayer": "00"}]}, {"RallyNo": 12, "startTime": 671.0435478, "endTime": 675.4293194, "startSide": 1, "winSide": 0, "score": [5, 6], "list": [{"StrikeNo": 1, "BallPosition": "S1", "StrikePosition": "S1", "StrikeTech": "Reverse", "GameAction": "Serve", "StrikeEffect": "L5", "SpinKind": "ND", "HitPlayer": "10"}]}, {"RallyNo": 13, "startTime": 696.2954037, "endTime": 705.5337802, "startSide": 0, "winSide": 1, "score": [6, 6], "list": [{"StrikeNo": 1, "BallPosition": "S1", "StrikePosition": "S1", "StrikeTech": "Pendulum", "GameAction": "Serve", "StrikeEffect": "L4", "SpinKind": "NT", "HitPlayer": "00"}, {"StrikeNo": 2, "BallPosition": "BH", "StrikePosition": "B", "StrikeTech": "Flick", "GameAction": "Receive", "StrikeEffect": "L3", "SpinKind": "SK", "HitPlayer": "10"}, {"StrikeNo": 3, "BallPosition": "BL", "StrikePosition": "B", "StrikeTech": "Topspin", "GameAction": "Stalemate", "StrikeEffect": "L4", "SpinKind": "NT", "HitPlayer": "00"}, {"StrikeNo": 4, "BallPosition": "ML", "StrikePosition": "B", "StrikeTech": "Others", "GameAction": "Defensive", "StrikeEffect": "L1", "SpinKind": "ND", "HitPlayer": "10"}, {"StrikeNo": 5, "BallPosition": "ML", "StrikePosition": "F", "StrikeTech": "Topspin", "GameAction": "Offensive", "StrikeEffect": "L5", "SpinKind": "ST", "HitPlayer": "00"}]}, {"RallyNo": 14, "startTime": 720.886739, "endTime": 729.9269359, "startSide": 0, "winSide": 0, "score": [6, 7], "list": [{"StrikeNo": 1, "BallPosition": "S2", "StrikePosition": "S2", "StrikeTech": "Pendulum", "GameAction": "Serve", "StrikeEffect": "L2", "SpinKind": "ND", "HitPlayer": "00"}, {"StrikeNo": 2, "BallPosition": "BH", "StrikePosition": "B", "StrikeTech": "Others", "GameAction": "Receive", "StrikeEffect": "L4", "SpinKind": "ND", "HitPlayer": "10"}, {"StrikeNo": 3, "BallPosition": "BL", "StrikePosition": "B", "StrikeTech": "Topspin", "GameAction": "Offensive", "StrikeEffect": "L2", "SpinKind": "ST", "HitPlayer": "00"}, {"StrikeNo": 4, "BallPosition": "ML", "StrikePosition": "B", "StrikeTech": "Others", "GameAction": "Defensive", "StrikeEffect": "L4", "SpinKind": "ND", "HitPlayer": "10"}, {"StrikeNo": 5, "BallPosition": "ML", "StrikePosition": "F", "StrikeTech": "Topspin", "GameAction": "Offensive", "StrikeEffect": "L1", "SpinKind": "ST", "HitPlayer": "00"}, {"StrikeNo": 6, "BallPosition": "FL", "StrikePosition": "F", "StrikeTech": "Block", "GameAction": "Defensive", "StrikeEffect": "L5", "SpinKind": "NT", "HitPlayer": "10"}]}, {"RallyNo": 15, "startTime": 748.2289583, "endTime": 753.6822508, "startSide": 1, "winSide": 0, "score": [7, 7], "list": [{"StrikeNo": 1, "BallPosition": "S1", "StrikePosition": "S1", "StrikeTech": "Reverse", "GameAction": "Serve", "StrikeEffect": "L4", "SpinKind": "NT", "HitPlayer": "10"}, {"StrikeNo": 2, "BallPosition": "FH", "StrikePosition": "F", "StrikeTech": "Topspin", "GameAction": "Receive", "StrikeEffect": "L1", "SpinKind": "NT", "HitPlayer": "00"}, {"StrikeNo": 3, "BallPosition": "FL", "StrikePosition": "F", "StrikeTech": "Block", "GameAction": "Defensive", "StrikeEffect": "L5", "SpinKind": "NT", "HitPlayer": "10"}]}, {"RallyNo": 16, "startTime": 767.4627803, "endTime": 775.535477, "startSide": 1, "winSide": 0, "score": [8, 7], "list": [{"StrikeNo": 1, "BallPosition": "S1", "StrikePosition": "S1", "StrikeTech": "Reverse", "GameAction": "Serve", "StrikeEffect": "L2", "SpinKind": "ND", "HitPlayer": "10"}, {"StrikeNo": 2, "BallPosition": "FS", "StrikePosition": "F", "StrikeTech": "Push", "GameAction": "Receive", "StrikeEffect": "L4", "SpinKind": "ND", "HitPlayer": "00"}, {"StrikeNo": 3, "BallPosition": "FL", "StrikePosition": "F", "StrikeTech": "Topspin", "GameAction": "Offensive", "StrikeEffect": "L2", "SpinKind": "ST", "HitPlayer": "10"}, {"StrikeNo": 4, "BallPosition": "BL", "StrikePosition": "B", "StrikeTech": "Block", "GameAction": "Defensive", "StrikeEffect": "L1", "SpinKind": "NT", "HitPlayer": "00"}, {"StrikeNo": 5, "BallPosition": "BL", "StrikePosition": "B", "StrikeTech": "Attack", "GameAction": "Offensive", "StrikeEffect": "L5", "SpinKind": "SK", "HitPlayer": "10"}]}, {"RallyNo": 17, "startTime": 793.5038614, "endTime": 803.7173709, "startSide": 0, "winSide": 1, "score": [9, 7], "list": [{"StrikeNo": 1, "BallPosition": "S2", "StrikePosition": "S2", "StrikeTech": "Pendulum", "GameAction": "Serve", "StrikeEffect": "L4", "SpinKind": "NT", "HitPlayer": "00"}, {"StrikeNo": 2, "BallPosition": "BL", "StrikePosition": "B", "StrikeTech": "Attack", "GameAction": "Receive", "StrikeEffect": "L3", "SpinKind": "SK", "HitPlayer": "10"}, {"StrikeNo": 3, "BallPosition": "FL", "StrikePosition": "F", "StrikeTech": "Topspin", "GameAction": "Stalemate", "StrikeEffect": "L3", "SpinKind": "NT", "HitPlayer": "00"}, {"StrikeNo": 4, "BallPosition": "ML", "StrikePosition": "B", "StrikeTech": "Attack", "GameAction": "Stalemate", "StrikeEffect": "L3", "SpinKind": "SK", "HitPlayer": "10"}, {"StrikeNo": 5, "BallPosition": "SP", "StrikePosition": "B", "StrikeTech": "Topspin", "GameAction": "Stalemate", "StrikeEffect": "L2", "SpinKind": "NT", "HitPlayer": "00"}, {"StrikeNo": 6, "BallPosition": "BL", "StrikePosition": "B", "StrikeTech": "Block", "GameAction": "Defensive", "StrikeEffect": "L1", "SpinKind": "SK", "HitPlayer": "10"}, {"StrikeNo": 7, "BallPosition": "ML", "StrikePosition": "P", "StrikeTech": "Topspin", "GameAction": "Offensive", "StrikeEffect": "L5", "SpinKind": "NT", "HitPlayer": "00"}]}, {"RallyNo": 18, "startTime": 823.5725798, "endTime": 831.7405265, "startSide": 0, "winSide": 0, "score": [9, 8], "list": [{"StrikeNo": 1, "BallPosition": "S1", "StrikePosition": "S1", "StrikeTech": "Pendulum", "GameAction": "Serve", "StrikeEffect": "L4", "SpinKind": "NT", "HitPlayer": "00"}, {"StrikeNo": 2, "BallPosition": "BL", "StrikePosition": "B", "StrikeTech": "Attack", "GameAction": "Receive", "StrikeEffect": "L3", "SpinKind": "SK", "HitPlayer": "10"}, {"StrikeNo": 3, "BallPosition": "FL", "StrikePosition": "F", "StrikeTech": "Topspin", "GameAction": "Stalemate", "StrikeEffect": "L2", "SpinKind": "NT", "HitPlayer": "00"}, {"StrikeNo": 4, "BallPosition": "FL", "StrikePosition": "F", "StrikeTech": "Block", "GameAction": "Defensive", "StrikeEffect": "L4", "SpinKind": "NT", "HitPlayer": "10"}, {"StrikeNo": 5, "BallPosition": "BL", "StrikePosition": "B", "StrikeTech": "Topspin", "GameAction": "Offensive", "StrikeEffect": "L1", "SpinKind": "NT", "HitPlayer": "00"}, {"StrikeNo": 6, "BallPosition": "BL", "StrikePosition": "B", "StrikeTech": "Attack", "GameAction": "Stalemate", "StrikeEffect": "L5", "SpinKind": "SK", "HitPlayer": "10"}]}, {"RallyNo": 19, "startTime": 852.2322983, "endTime": 861.1808494, "startSide": 1, "winSide": 1, "score": [10, 8], "list": [{"StrikeNo": 1, "BallPosition": "S1", "StrikePosition": "S1", "StrikeTech": "Pendulum", "GameAction": "Serve", "StrikeEffect": "L2", "SpinKind": "ND", "HitPlayer": "10"}, {"StrikeNo": 2, "BallPosition": "BS", "StrikePosition": "B", "StrikeTech": "Push", "GameAction": "Receive", "StrikeEffect": "L4", "SpinKind": "ND", "HitPlayer": "00"}, {"StrikeNo": 3, "BallPosition": "BL", "StrikePosition": "B", "StrikeTech": "Topspin", "GameAction": "Offensive", "StrikeEffect": "L2", "SpinKind": "ST", "HitPlayer": "10"}, {"StrikeNo": 4, "BallPosition": "BL", "StrikePosition": "B", "StrikeTech": "Block", "GameAction": "Defensive", "StrikeEffect": "L4", "SpinKind": "NT", "HitPlayer": "00"}, {"StrikeNo": 5, "BallPosition": "BL", "StrikePosition": "B", "StrikeTech": "Attack", "GameAction": "Offensive", "StrikeEffect": "L2", "SpinKind": "SK", "HitPlayer": "10"}, {"StrikeNo": 6, "BallPosition": "BL", "StrikePosition": "B", "StrikeTech": "Block", "GameAction": "Defensive", "StrikeEffect": "L4", "SpinKind": "NT", "HitPlayer": "00"}, {"StrikeNo": 7, "BallPosition": "BL", "StrikePosition": "P", "StrikeTech": "Attack", "GameAction": "Offensive", "StrikeEffect": "L1", "SpinKind": "NT", "HitPlayer": "10"}, {"StrikeNo": 8, "BallPosition": "BL", "StrikePosition": "B", "StrikeTech": "Block", "GameAction": "Defensive", "StrikeEffect": "L5", "SpinKind": "NT", "HitPlayer": "00"}]}, {"RallyNo": 20, "startTime": 880.5541834, "endTime": 887.2207262, "startSide": 1, "winSide": 0, "score": [10, 9], "list": [{"StrikeNo": 1, "BallPosition": "S1", "StrikePosition": "S1", "StrikeTech": "Reverse", "GameAction": "Serve", "StrikeEffect": "L4", "SpinKind": "NT", "HitPlayer": "10"}, {"StrikeNo": 2, "BallPosition": "BL", "StrikePosition": "B", "StrikeTech": "Topspin", "GameAction": "Receive", "StrikeEffect": "L2", "SpinKind": "NT", "HitPlayer": "00"}, {"StrikeNo": 3, "BallPosition": "ML", "StrikePosition": "B", "StrikeTech": "Block", "GameAction": "Defensive", "StrikeEffect": "L4", "SpinKind": "SK", "HitPlayer": "10"}, {"StrikeNo": 4, "BallPosition": "BL", "StrikePosition": "B", "StrikeTech": "Topspin", "GameAction": "Offensive", "StrikeEffect": "L1", "SpinKind": "NT", "HitPlayer": "00"}, {"StrikeNo": 5, "BallPosition": "BL", "StrikePosition": "B", "StrikeTech": "Block", "GameAction": "Defensive", "StrikeEffect": "L5", "SpinKind": "SK", "HitPlayer": "10"}]}]}, {"GameNo": 3, "result": [11, 9], "score": [2, 0], "list": [{"RallyNo": 1, "startTime": 987.4611228, "endTime": 993.805603, "startSide": 1, "winSide": 1, "score": [0, 0], "list": [{"StrikeNo": 1, "BallPosition": "S2", "StrikePosition": "S2", "StrikeTech": "Reverse", "GameAction": "Serve", "StrikeEffect": "L1", "SpinKind": "NT", "HitPlayer": "10"}, {"StrikeNo": 2, "BallPosition": "BH", "StrikePosition": "B", "StrikeTech": "Push", "GameAction": "Receive", "StrikeEffect": "L5", "SpinKind": "ND", "HitPlayer": "00"}]}, {"RallyNo": 2, "startTime": 1002.179528, "endTime": 1010.3305084, "startSide": 1, "winSide": 0, "score": [0, 1], "list": [{"StrikeNo": 1, "BallPosition": "S2", "StrikePosition": "S2", "StrikeTech": "Reverse", "GameAction": "Serve", "StrikeEffect": "L2", "SpinKind": "ND", "HitPlayer": "10"}, {"StrikeNo": 2, "BallPosition": "MH", "StrikePosition": "B", "StrikeTech": "Push", "GameAction": "Receive", "StrikeEffect": "L4", "SpinKind": "ND", "HitPlayer": "00"}, {"StrikeNo": 3, "BallPosition": "BL", "StrikePosition": "B", "StrikeTech": "Topspin", "GameAction": "Offensive", "StrikeEffect": "L2", "SpinKind": "ST", "HitPlayer": "10"}, {"StrikeNo": 4, "BallPosition": "BL", "StrikePosition": "B", "StrikeTech": "Block", "GameAction": "Defensive", "StrikeEffect": "L4", "SpinKind": "NT", "HitPlayer": "00"}, {"StrikeNo": 5, "BallPosition": "BL", "StrikePosition": "B", "StrikeTech": "Attack", "GameAction": "Offensive", "StrikeEffect": "L3", "SpinKind": "SK", "HitPlayer": "10"}, {"StrikeNo": 6, "BallPosition": "BL", "StrikePosition": "B", "StrikeTech": "Topspin", "GameAction": "Stalemate", "StrikeEffect": "L1", "SpinKind": "NT", "HitPlayer": "00"}, {"StrikeNo": 7, "BallPosition": "ML", "StrikePosition": "B", "StrikeTech": "Block", "GameAction": "Defensive", "StrikeEffect": "L5", "SpinKind": "SK", "HitPlayer": "10"}]}, {"RallyNo": 3, "startTime": 1023.3846758, "endTime": 1032.6932815, "startSide": 0, "winSide": 1, "score": [1, 1], "list": [{"StrikeNo": 1, "BallPosition": "S2", "StrikePosition": "S2", "StrikeTech": "Pendulum", "GameAction": "Serve", "StrikeEffect": "L2", "SpinKind": "ND", "HitPlayer": "00"}, {"StrikeNo": 2, "BallPosition": "MS", "StrikePosition": "B", "StrikeTech": "Others", "GameAction": "Receive", "StrikeEffect": "L4", "SpinKind": "ND", "HitPlayer": "10"}, {"StrikeNo": 3, "BallPosition": "BL", "StrikePosition": "B", "StrikeTech": "Topspin", "GameAction": "Offensive", "StrikeEffect": "L2", "SpinKind": "ST", "HitPlayer": "00"}, {"StrikeNo": 4, "BallPosition": "ML", "StrikePosition": "B", "StrikeTech": "Others", "GameAction": "Defensive", "StrikeEffect": "L4", "SpinKind": "ND", "HitPlayer": "10"}, {"StrikeNo": 5, "BallPosition": "ML", "StrikePosition": "F", "StrikeTech": "Topspin", "GameAction": "Offensive", "StrikeEffect": "L3", "SpinKind": "ST", "HitPlayer": "00"}, {"StrikeNo": 6, "BallPosition": "ML", "StrikePosition": "T", "StrikeTech": "Attack", "GameAction": "Stalemate", "StrikeEffect": "L1", "SpinKind": "SK", "HitPlayer": "10"}, {"StrikeNo": 7, "BallPosition": "BL", "StrikePosition": "B", "StrikeTech": "Topspin", "GameAction": "Stalemate", "StrikeEffect": "L5", "SpinKind": "NT", "HitPlayer": "00"}]}, {"RallyNo": 4, "startTime": 1048.6637612, "endTime": 1055.2815123, "startSide": 0, "winSide": 0, "score": [1, 2], "list": [{"StrikeNo": 1, "BallPosition": "S2", "StrikePosition": "S2", "StrikeTech": "Pendulum", "GameAction": "Serve", "StrikeEffect": "L1", "SpinKind": "ND", "HitPlayer": "00"}, {"StrikeNo": 2, "BallPosition": "BS", "StrikePosition": "B", "StrikeTech": "Flick", "GameAction": "Receive", "StrikeEffect": "L5", "SpinKind": "SK", "HitPlayer": "10"}]}, {"RallyNo": 5, "startTime": 1064.8545962, "endTime": 1071.7609306, "startSide": 1, "winSide": 1, "score": [2, 2], "list": [{"StrikeNo": 1, "BallPosition": "S1", "StrikePosition": "S1", "StrikeTech": "Pendulum", "GameAction": "Serve", "StrikeEffect": "L4", "SpinKind": "ND", "HitPlayer": "10"}, {"StrikeNo": 2, "BallPosition": "BH", "StrikePosition": "B", "StrikeTech": "Topspin", "GameAction": "Receive", "StrikeEffect": "L3", "SpinKind": "ST", "HitPlayer": "00"}, {"StrikeNo": 3, "BallPosition": "BL", "StrikePosition": "B", "StrikeTech": "Attack", "GameAction": "Stalemate", "StrikeEffect": "L1", "SpinKind": "SK", "HitPlayer": "10"}, {"StrikeNo": 4, "BallPosition": "FL", "StrikePosition": "F", "StrikeTech": "Topspin", "GameAction": "Stalemate", "StrikeEffect": "L5", "SpinKind": "NT", "HitPlayer": "00"}]}, {"RallyNo": 6, "startTime": 1080.3624189, "endTime": 1085.603149, "startSide": 1, "winSide": 0, "score": [2, 3], "list": [{"StrikeNo": 1, "BallPosition": "S1", "StrikePosition": "S1", "StrikeTech": "Reverse", "GameAction": "Serve", "StrikeEffect": "L4", "SpinKind": "NT", "HitPlayer": "10"}, {"StrikeNo": 2, "BallPosition": "BH", "StrikePosition": "B", "StrikeTech": "Topspin", "GameAction": "Receive", "StrikeEffect": "L1", "SpinKind": "NT", "HitPlayer": "00"}, {"StrikeNo": 3, "BallPosition": "BL", "StrikePosition": "B", "StrikeTech": "Block", "GameAction": "Defensive", "StrikeEffect": "L5", "SpinKind": "SK", "HitPlayer": "10"}]}, {"RallyNo": 7, "startTime": 1107.2943949, "endTime": 1113.9461747, "startSide": 0, "winSide": 1, "score": [3, 3], "list": [{"StrikeNo": 1, "BallPosition": "S2", "StrikePosition": "S2", "StrikeTech": "Pendulum", "GameAction": "Serve", "StrikeEffect": "L4", "SpinKind": "ND", "HitPlayer": "00"}, {"StrikeNo": 2, "BallPosition": "MH", "StrikePosition": "B", "StrikeTech": "Twist", "GameAction": "Receive", "StrikeEffect": "L1", "SpinKind": "SK", "HitPlayer": "10"}, {"StrikeNo": 3, "BallPosition": "BL", "StrikePosition": "B", "StrikeTech": "Topspin", "GameAction": "Stalemate", "StrikeEffect": "L5", "SpinKind": "NT", "HitPlayer": "00"}]}, {"RallyNo": 8, "startTime": 1129.8041881, "endTime": 1135.9636266, "startSide": 0, "winSide": 0, "score": [3, 4], "list": [{"StrikeNo": 1, "BallPosition": "S1", "StrikePosition": "S1", "StrikeTech": "Pendulum", "GameAction": "Serve", "StrikeEffect": "L2", "SpinKind": "ND", "HitPlayer": "00"}, {"StrikeNo": 2, "BallPosition": "FS", "StrikePosition": "F", "StrikeTech": "Short", "GameAction": "Receive", "StrikeEffect": "L4", "SpinKind": "ND", "HitPlayer": "10"}, {"StrikeNo": 3, "BallPosition": "BH", "StrikePosition": "B", "StrikeTech": "Topspin", "GameAction": "Offensive", "StrikeEffect": "L1", "SpinKind": "ST", "HitPlayer": "00"}, {"StrikeNo": 4, "BallPosition": "BL", "StrikePosition": "B", "StrikeTech": "Block", "GameAction": "Defensive", "StrikeEffect": "L5", "SpinKind": "SK", "HitPlayer": "10"}]}, {"RallyNo": 9, "startTime": 1147.384981, "endTime": 1151.3386899, "startSide": 1, "winSide": 1, "score": [4, 4], "list": [{"StrikeNo": 1, "BallPosition": "S1", "StrikePosition": "S1", "StrikeTech": "Reverse", "GameAction": "Serve", "StrikeEffect": "L1", "SpinKind": "ND", "HitPlayer": "10"}, {"StrikeNo": 2, "BallPosition": "FS", "StrikePosition": "F", "StrikeTech": "Short", "GameAction": "Receive", "StrikeEffect": "L5", "SpinKind": "ND", "HitPlayer": "00"}]}, {"RallyNo": 10, "startTime": 1161.8586568, "endTime": 1169.8007493, "startSide": 1, "winSide": 0, "score": [4, 5], "list": [{"StrikeNo": 1, "BallPosition": "S1", "StrikePosition": "S1", "StrikeTech": "Reverse", "GameAction": "Serve", "StrikeEffect": "L3", "SpinKind": "ND", "HitPlayer": "10"}, {"StrikeNo": 2, "BallPosition": "FS", "StrikePosition": "F", "StrikeTech": "Short", "GameAction": "Receive", "StrikeEffect": "L3", "SpinKind": "ND", "HitPlayer": "00"}, {"StrikeNo": 3, "BallPosition": "FS", "StrikePosition": "F", "StrikeTech": "Short", "GameAction": "Controlled", "StrikeEffect": "L4", "SpinKind": "ND", "HitPlayer": "10"}, {"StrikeNo": 4, "BallPosition": "MH", "StrikePosition": "B", "StrikeTech": "Topspin", "GameAction": "Offensive", "StrikeEffect": "L2", "SpinKind": "ST", "HitPlayer": "00"}, {"StrikeNo": 5, "BallPosition": "BL", "StrikePosition": "B", "StrikeTech": "Block", "GameAction": "Defensive", "StrikeEffect": "L4", "SpinKind": "SK", "HitPlayer": "10"}, {"StrikeNo": 6, "BallPosition": "BL", "StrikePosition": "B", "StrikeTech": "Topspin", "GameAction": "Offensive", "StrikeEffect": "L1", "SpinKind": "NT", "HitPlayer": "00"}, {"StrikeNo": 7, "BallPosition": "BL", "StrikePosition": "B", "StrikeTech": "Attack", "GameAction": "Stalemate", "StrikeEffect": "L5", "SpinKind": "SK", "HitPlayer": "10"}]}, {"RallyNo": 11, "startTime": 1188.076717, "endTime": 1194.7013718, "startSide": 0, "winSide": 1, "score": [5, 5], "list": [{"StrikeNo": 1, "BallPosition": "S1", "StrikePosition": "S1", "StrikeTech": "Pendulum", "GameAction": "Serve", "StrikeEffect": "L4", "SpinKind": "NT", "HitPlayer": "00"}, {"StrikeNo": 2, "BallPosition": "ML", "StrikePosition": "B", "StrikeTech": "Attack", "GameAction": "Receive", "StrikeEffect": "L1", "SpinKind": "SK", "HitPlayer": "10"}, {"StrikeNo": 3, "BallPosition": "FL", "StrikePosition": "F", "StrikeTech": "Topspin", "GameAction": "Stalemate", "StrikeEffect": "L5", "SpinKind": "NT", "HitPlayer": "00"}]}, {"RallyNo": 12, "startTime": 1210.6378098, "endTime": 1219.9056655, "startSide": 0, "winSide": 0, "score": [5, 6], "list": [{"StrikeNo": 1, "BallPosition": "S1", "StrikePosition": "S1", "StrikeTech": "Pendulum", "GameAction": "Serve", "StrikeEffect": "L4", "SpinKind": "NT", "HitPlayer": "00"}, {"StrikeNo": 2, "BallPosition": "BL", "StrikePosition": "B", "StrikeTech": "Attack", "GameAction": "Receive", "StrikeEffect": "L3", "SpinKind": "SK", "HitPlayer": "10"}, {"StrikeNo": 3, "BallPosition": "BL", "StrikePosition": "B", "StrikeTech": "Topspin", "GameAction": "Stalemate", "StrikeEffect": "L3", "SpinKind": "NT", "HitPlayer": "00"}, {"StrikeNo": 4, "BallPosition": "ML", "StrikePosition": "P", "StrikeTech": "Topspin", "GameAction": "Stalemate", "StrikeEffect": "L3", "SpinKind": "NT", "HitPlayer": "10"}, {"StrikeNo": 5, "BallPosition": "FL", "StrikePosition": "F", "StrikeTech": "Topspin", "GameAction": "Stalemate", "StrikeEffect": "L1", "SpinKind": "NT", "HitPlayer": "00"}, {"StrikeNo": 6, "BallPosition": "BL", "StrikePosition": "B", "StrikeTech": "Block", "GameAction": "Defensive", "StrikeEffect": "L5", "SpinKind": "WT", "HitPlayer": "10"}]}, {"RallyNo": 13, "startTime": 1241.350333, "endTime": 1247.8160423, "startSide": 1, "winSide": 0, "score": [6, 6], "list": [{"StrikeNo": 1, "BallPosition": "S1", "StrikePosition": "S1", "StrikeTech": "Reverse", "GameAction": "Serve", "StrikeEffect": "L4", "SpinKind": "ND", "HitPlayer": "10"}, {"StrikeNo": 2, "BallPosition": "BH", "StrikePosition": "P", "StrikeTech": "Topspin", "GameAction": "Receive", "StrikeEffect": "L1", "SpinKind": "ST", "HitPlayer": "00"}, {"StrikeNo": 3, "BallPosition": "BL", "StrikePosition": "B", "StrikeTech": "Block", "GameAction": "Defensive", "StrikeEffect": "L5", "SpinKind": "SK", "HitPlayer": "10"}]}, {"RallyNo": 14, "startTime": 1349.0768352, "endTime": 1354.345461, "startSide": 1, "winSide": 0, "score": [7, 6], "list": [{"StrikeNo": 1, "BallPosition": "S1", "StrikePosition": "S1", "StrikeTech": "Reverse", "GameAction": "Serve", "StrikeEffect": "L4", "SpinKind": "NT", "HitPlayer": "10"}, {"StrikeNo": 2, "BallPosition": "BL", "StrikePosition": "B", "StrikeTech": "Topspin", "GameAction": "Receive", "StrikeEffect": "L1", "SpinKind": "NT", "HitPlayer": "00"}, {"StrikeNo": 3, "BallPosition": "BL", "StrikePosition": "B", "StrikeTech": "Attack", "GameAction": "Stalemate", "StrikeEffect": "L5", "SpinKind": "SK", "HitPlayer": "10"}]}, {"RallyNo": 15, "startTime": 1369.8416702, "endTime": 1378.8531508, "startSide": 0, "winSide": 1, "score": [8, 6], "list": [{"StrikeNo": 1, "BallPosition": "S1", "StrikePosition": "S1", "StrikeTech": "Pendulum", "GameAction": "Serve", "StrikeEffect": "L4", "SpinKind": "NT", "HitPlayer": "00"}, {"StrikeNo": 2, "BallPosition": "BL", "StrikePosition": "B", "StrikeTech": "Attack", "GameAction": "Receive", "StrikeEffect": "L3", "SpinKind": "SK", "HitPlayer": "10"}, {"StrikeNo": 3, "BallPosition": "FL", "StrikePosition": "F", "StrikeTech": "Topspin", "GameAction": "Stalemate", "StrikeEffect": "L3", "SpinKind": "NT", "HitPlayer": "00"}, {"StrikeNo": 4, "BallPosition": "FL", "StrikePosition": "F", "StrikeTech": "Attack", "GameAction": "Stalemate", "StrikeEffect": "L1", "SpinKind": "NT", "HitPlayer": "10"}, {"StrikeNo": 5, "BallPosition": "BL", "StrikePosition": "B", "StrikeTech": "Block", "GameAction": "Defensive", "StrikeEffect": "L5", "SpinKind": "NT", "HitPlayer": "00"}]}, {"RallyNo": 16, "startTime": 1391.8063805, "endTime": 1399.2042774, "startSide": 0, "winSide": 1, "score": [8, 7], "list": [{"StrikeNo": 1, "BallPosition": "S1", "StrikePosition": "S1", "StrikeTech": "Pendulum", "GameAction": "Serve", "StrikeEffect": "L2", "SpinKind": "ND", "HitPlayer": "00"}, {"StrikeNo": 2, "BallPosition": "BS", "StrikePosition": "P", "StrikeTech": "Short", "GameAction": "Receive", "StrikeEffect": "L1", "SpinKind": "ND", "HitPlayer": "10"}, {"StrikeNo": 3, "BallPosition": "BH", "StrikePosition": "B", "StrikeTech": "Topspin", "GameAction": "Offensive", "StrikeEffect": "L5", "SpinKind": "ST", "HitPlayer": "00"}]}, {"RallyNo": 17, "startTime": 1412.6919655, "endTime": 1420.2474459, "startSide": 1, "winSide": 1, "score": [8, 8], "list": [{"StrikeNo": 1, "BallPosition": "S2", "StrikePosition": "S2", "StrikeTech": "Reverse", "GameAction": "Serve", "StrikeEffect": "L4", "SpinKind": "ND", "HitPlayer": "10"}, {"StrikeNo": 2, "BallPosition": "BL", "StrikePosition": "P", "StrikeTech": "Topspin", "GameAction": "Receive", "StrikeEffect": "L2", "SpinKind": "ST", "HitPlayer": "00"}, {"StrikeNo": 3, "BallPosition": "FL", "StrikePosition": "F", "StrikeTech": "Block", "GameAction": "Defensive", "StrikeEffect": "L4", "SpinKind": "NT", "HitPlayer": "10"}, {"StrikeNo": 4, "BallPosition": "BL", "StrikePosition": "B", "StrikeTech": "Topspin", "GameAction": "Offensive", "StrikeEffect": "L2", "SpinKind": "NT", "HitPlayer": "00"}, {"StrikeNo": 5, "BallPosition": "BL", "StrikePosition": "B", "StrikeTech": "Block", "GameAction": "Defensive", "StrikeEffect": "L1", "SpinKind": "SK", "HitPlayer": "10"}, {"StrikeNo": 6, "BallPosition": "BL", "StrikePosition": "P", "StrikeTech": "Topspin", "GameAction": "Offensive", "StrikeEffect": "L5", "SpinKind": "NT", "HitPlayer": "00"}]}, {"RallyNo": 18, "startTime": 1438.4963219, "endTime": 1445.8792893, "startSide": 1, "winSide": 0, "score": [8, 9], "list": [{"StrikeNo": 1, "BallPosition": "S2", "StrikePosition": "S2", "StrikeTech": "Reverse", "GameAction": "Serve", "StrikeEffect": "L4", "SpinKind": "ND", "HitPlayer": "10"}, {"StrikeNo": 2, "BallPosition": "MH", "StrikePosition": "F", "StrikeTech": "Topspin", "GameAction": "Receive", "StrikeEffect": "L2", "SpinKind": "ST", "HitPlayer": "00"}, {"StrikeNo": 3, "BallPosition": "FL", "StrikePosition": "F", "StrikeTech": "Block", "GameAction": "Defensive", "StrikeEffect": "L4", "SpinKind": "NT", "HitPlayer": "10"}, {"StrikeNo": 4, "BallPosition": "ML", "StrikePosition": "F", "StrikeTech": "Topspin", "GameAction": "Offensive", "StrikeEffect": "L1", "SpinKind": "NT", "HitPlayer": "00"}, {"StrikeNo": 5, "BallPosition": "FL", "StrikePosition": "F", "StrikeTech": "Block", "GameAction": "Defensive", "StrikeEffect": "L5", "SpinKind": "WT", "HitPlayer": "10"}]}, {"RallyNo": 19, "startTime": 1474.1470606, "endTime": 1480.9775409, "startSide": 0, "winSide": 0, "score": [9, 9], "list": [{"StrikeNo": 1, "BallPosition": "S2", "StrikePosition": "S2", "StrikeTech": "Pendulum", "GameAction": "Serve", "StrikeEffect": "L3", "SpinKind": "ND", "HitPlayer": "00"}, {"StrikeNo": 2, "BallPosition": "FS", "StrikePosition": "F", "StrikeTech": "Short", "GameAction": "Receive", "StrikeEffect": "L3", "SpinKind": "ND", "HitPlayer": "10"}, {"StrikeNo": 3, "BallPosition": "FS", "StrikePosition": "T", "StrikeTech": "Push", "GameAction": "Controlled", "StrikeEffect": "L1", "SpinKind": "ND", "HitPlayer": "00"}, {"StrikeNo": 4, "BallPosition": "BL", "StrikePosition": "B", "StrikeTech": "Topspin", "GameAction": "Offensive", "StrikeEffect": "L5", "SpinKind": "ST", "HitPlayer": "10"}]}, {"RallyNo": 20, "startTime": 1515.0461046, "endTime": 1523.4377726, "startSide": 0, "winSide": 0, "score": [10, 9], "list": [{"StrikeNo": 1, "BallPosition": "S2", "StrikePosition": "S2", "StrikeTech": "Pendulum", "GameAction": "Serve", "StrikeEffect": "L4", "SpinKind": "NT", "HitPlayer": "00"}, {"StrikeNo": 2, "BallPosition": "ML", "StrikePosition": "B", "StrikeTech": "Attack", "GameAction": "Receive", "StrikeEffect": "L3", "SpinKind": "SK", "HitPlayer": "10"}, {"StrikeNo": 3, "BallPosition": "BL", "StrikePosition": "B", "StrikeTech": "Topspin", "GameAction": "Stalemate", "StrikeEffect": "L2", "SpinKind": "NT", "HitPlayer": "00"}, {"StrikeNo": 4, "BallPosition": "BL", "StrikePosition": "B", "StrikeTech": "Block", "GameAction": "Defensive", "StrikeEffect": "L4", "SpinKind": "SK", "HitPlayer": "10"}, {"StrikeNo": 5, "BallPosition": "ML", "StrikePosition": "P", "StrikeTech": "Topspin", "GameAction": "Offensive", "StrikeEffect": "L1", "SpinKind": "NT", "HitPlayer": "00"}, {"StrikeNo": 6, "BallPosition": "BL", "StrikePosition": "B", "StrikeTech": "Block", "GameAction": "Defensive", "StrikeEffect": "L5", "SpinKind": "WT", "HitPlayer": "10"}]}]}, {"GameNo": 4, "result": [13, 15], "score": [3, 0], "list": [{"RallyNo": 1, "startTime": 1629.8761275, "endTime": 1637.6945037, "startSide": 0, "winSide": 1, "score": [0, 0], "list": [{"StrikeNo": 1, "BallPosition": "S2", "StrikePosition": "S2", "StrikeTech": "Pendulum", "GameAction": "Serve", "StrikeEffect": "L2", "SpinKind": "ND", "HitPlayer": "00"}, {"StrikeNo": 2, "BallPosition": "FS", "StrikePosition": "T", "StrikeTech": "Others", "GameAction": "Receive", "StrikeEffect": "L4", "SpinKind": "NT", "HitPlayer": "10"}, {"StrikeNo": 3, "BallPosition": "FL", "StrikePosition": "F", "StrikeTech": "Topspin", "GameAction": "Offensive", "StrikeEffect": "L2", "SpinKind": "ST", "HitPlayer": "00"}, {"StrikeNo": 4, "BallPosition": "FL", "StrikePosition": "T", "StrikeTech": "Block", "GameAction": "Defensive", "StrikeEffect": "L1", "SpinKind": "SK", "HitPlayer": "10"}, {"StrikeNo": 5, "BallPosition": "BL", "StrikePosition": "B", "StrikeTech": "Others", "GameAction": "Defensive", "StrikeEffect": "L5", "SpinKind": "WT", "HitPlayer": "00"}]}, {"RallyNo": 2, "startTime": 1650.2851502, "endTime": 1656.1749636, "startSide": 0, "winSide": 0, "score": [0, 1], "list": [{"StrikeNo": 1, "BallPosition": "S2", "StrikePosition": "S2", "StrikeTech": "Pendulum", "GameAction": "Serve", "StrikeEffect": "L1", "SpinKind": "ND", "HitPlayer": "00"}, {"StrikeNo": 2, "BallPosition": "FS", "StrikePosition": "F", "StrikeTech": "Short", "GameAction": "Receive", "StrikeEffect": "L5", "SpinKind": "ND", "HitPlayer": "10"}]}, {"RallyNo": 3, "startTime": 1667.7194016, "endTime": 1675.9493821, "startSide": 1, "winSide": 1, "score": [1, 1], "list": [{"StrikeNo": 1, "BallPosition": "S1", "StrikePosition": "S1", "StrikeTech": "Reverse", "GameAction": "Serve", "StrikeEffect": "L2", "SpinKind": "ND", "HitPlayer": "10"}, {"StrikeNo": 2, "BallPosition": "BS", "StrikePosition": "B", "StrikeTech": "Push", "GameAction": "Receive", "StrikeEffect": "L4", "SpinKind": "ND", "HitPlayer": "00"}, {"StrikeNo": 3, "BallPosition": "BL", "StrikePosition": "B", "StrikeTech": "Topspin", "GameAction": "Offensive", "StrikeEffect": "L3", "SpinKind": "ST", "HitPlayer": "10"}, {"StrikeNo": 4, "BallPosition": "BL", "StrikePosition": "B", "StrikeTech": "Topspin", "GameAction": "Stalemate", "StrikeEffect": "L3", "SpinKind": "NT", "HitPlayer": "00"}, {"StrikeNo": 5, "BallPosition": "BL", "StrikePosition": "B", "StrikeTech": "Attack", "GameAction": "Stalemate", "StrikeEffect": "L3", "SpinKind": "SK", "HitPlayer": "10"}, {"StrikeNo": 6, "BallPosition": "BL", "StrikePosition": "B", "StrikeTech": "Topspin", "GameAction": "Stalemate", "StrikeEffect": "L2", "SpinKind": "NT", "HitPlayer": "00"}, {"StrikeNo": 7, "BallPosition": "ML", "StrikePosition": "B", "StrikeTech": "Block", "GameAction": "Defensive", "StrikeEffect": "L1", "SpinKind": "SK", "HitPlayer": "10"}, {"StrikeNo": 8, "BallPosition": "FL", "StrikePosition": "F", "StrikeTech": "Topspin", "GameAction": "Offensive", "StrikeEffect": "L5", "SpinKind": "NT", "HitPlayer": "00"}]}, {"RallyNo": 4, "startTime": 1684.5471325, "endTime": 1689.1549327, "startSide": 1, "winSide": 0, "score": [1, 2], "list": [{"StrikeNo": 1, "BallPosition": "S2", "StrikePosition": "S2", "StrikeTech": "Reverse", "GameAction": "Serve", "StrikeEffect": "L5", "SpinKind": "ND", "HitPlayer": "10"}]}, {"RallyNo": 5, "startTime": 1700.7345791, "endTime": 1707.4250177, "startSide": 0, "winSide": 1, "score": [2, 2], "list": [{"StrikeNo": 1, "BallPosition": "S2", "StrikePosition": "S2", "StrikeTech": "Pendulum", "GameAction": "Serve", "StrikeEffect": "L4", "SpinKind": "NT", "HitPlayer": "00"}, {"StrikeNo": 2, "BallPosition": "ML", "StrikePosition": "B", "StrikeTech": "Attack", "GameAction": "Receive", "StrikeEffect": "L1", "SpinKind": "SK", "HitPlayer": "10"}, {"StrikeNo": 3, "BallPosition": "FL", "StrikePosition": "F", "StrikeTech": "Topspin", "GameAction": "Stalemate", "StrikeEffect": "L5", "SpinKind": "NT", "HitPlayer": "00"}]}, {"RallyNo": 6, "startTime": 1720.0137889, "endTime": 1727.7964776, "startSide": 0, "winSide": 1, "score": [2, 3], "list": [{"StrikeNo": 1, "BallPosition": "S2", "StrikePosition": "S2", "StrikeTech": "Pendulum", "GameAction": "Serve", "StrikeEffect": "L4", "SpinKind": "NT", "HitPlayer": "00"}, {"StrikeNo": 2, "BallPosition": "FH", "StrikePosition": "T", "StrikeTech": "Flick", "GameAction": "Receive", "StrikeEffect": "L1", "SpinKind": "SK", "HitPlayer": "10"}, {"StrikeNo": 3, "BallPosition": "FL", "StrikePosition": "F", "StrikeTech": "Topspin", "GameAction": "Stalemate", "StrikeEffect": "L5", "SpinKind": "NT", "HitPlayer": "00"}]}, {"RallyNo": 7, "startTime": 1750.6774783, "endTime": 1756.1971458, "startSide": 1, "winSide": 0, "score": [2, 4], "list": [{"StrikeNo": 1, "BallPosition": "S1", "StrikePosition": "S1", "StrikeTech": "Reverse", "GameAction": "Serve", "StrikeEffect": "L4", "SpinKind": "NT", "HitPlayer": "10"}, {"StrikeNo": 2, "BallPosition": "BS", "StrikePosition": "B", "StrikeTech": "Twist", "GameAction": "Receive", "StrikeEffect": "L1", "SpinKind": "NT", "HitPlayer": "00"}, {"StrikeNo": 3, "BallPosition": "BL", "StrikePosition": "B", "StrikeTech": "Block", "GameAction": "Defensive", "StrikeEffect": "L5", "SpinKind": "SK", "HitPlayer": "10"}]}, {"RallyNo": 8, "startTime": 1765.6610006, "endTime": 1774.2678562, "startSide": 1, "winSide": 1, "score": [3, 4], "list": [{"StrikeNo": 1, "BallPosition": "S1", "StrikePosition": "S1", "StrikeTech": "Reverse", "GameAction": "Serve", "StrikeEffect": "L2", "SpinKind": "ND", "HitPlayer": "10"}, {"StrikeNo": 2, "BallPosition": "FS", "StrikePosition": "F", "StrikeTech": "Short", "GameAction": "Receive", "StrikeEffect": "L4", "SpinKind": "ND", "HitPlayer": "00"}, {"StrikeNo": 3, "BallPosition": "MS", "StrikePosition": "F", "StrikeTech": "Flick", "GameAction": "Offensive", "StrikeEffect": "L3", "SpinKind": "NT", "HitPlayer": "10"}, {"StrikeNo": 4, "BallPosition": "FL", "StrikePosition": "F", "StrikeTech": "Topspin", "GameAction": "Stalemate", "StrikeEffect": "L3", "SpinKind": "NT", "HitPlayer": "00"}, {"StrikeNo": 5, "BallPosition": "FL", "StrikePosition": "F", "StrikeTech": "Topspin", "GameAction": "Stalemate", "StrikeEffect": "L1", "SpinKind": "NT", "HitPlayer": "10"}, {"StrikeNo": 6, "BallPosition": "BL", "StrikePosition": "B", "StrikeTech": "Block", "GameAction": "Defensive", "StrikeEffect": "L5", "SpinKind": "NT", "HitPlayer": "00"}]}, {"RallyNo": 9, "startTime": 1788.8916483, "endTime": 1796.519462, "startSide": 0, "winSide": 0, "score": [3, 5], "list": [{"StrikeNo": 1, "BallPosition": "S1", "StrikePosition": "S1", "StrikeTech": "Pendulum", "GameAction": "Serve", "StrikeEffect": "L1", "SpinKind": "NT", "HitPlayer": "00"}, {"StrikeNo": 2, "BallPosition": "ML", "StrikePosition": "B", "StrikeTech": "Attack", "GameAction": "Receive", "StrikeEffect": "L5", "SpinKind": "SK", "HitPlayer": "10"}]}, {"RallyNo": 10, "startTime": 1807.754504, "endTime": 1813.2867549, "startSide": 0, "winSide": 0, "score": [4, 5], "list": [{"StrikeNo": 1, "BallPosition": "S1", "StrikePosition": "S1", "StrikeTech": "Pendulum", "GameAction": "Serve", "StrikeEffect": "L1", "SpinKind": "NT", "HitPlayer": "00"}, {"StrikeNo": 2, "BallPosition": "BL", "StrikePosition": "P", "StrikeTech": "Topspin", "GameAction": "Receive", "StrikeEffect": "L5", "SpinKind": "NT", "HitPlayer": "10"}]}, {"RallyNo": 11, "startTime": 1824.8899012, "endTime": 1833.4606604, "startSide": 1, "winSide": 0, "score": [5, 5], "list": [{"StrikeNo": 1, "BallPosition": "S1", "StrikePosition": "S1", "StrikeTech": "Pendulum", "GameAction": "Serve", "StrikeEffect": "L4", "SpinKind": "NT", "HitPlayer": "10"}, {"StrikeNo": 2, "BallPosition": "BL", "StrikePosition": "B", "StrikeTech": "Topspin", "GameAction": "Receive", "StrikeEffect": "L2", "SpinKind": "NT", "HitPlayer": "00"}, {"StrikeNo": 3, "BallPosition": "BL", "StrikePosition": "B", "StrikeTech": "Block", "GameAction": "Defensive", "StrikeEffect": "L4", "SpinKind": "SK", "HitPlayer": "10"}, {"StrikeNo": 4, "BallPosition": "FL", "StrikePosition": "F", "StrikeTech": "Topspin", "GameAction": "Offensive", "StrikeEffect": "L2", "SpinKind": "NT", "HitPlayer": "00"}, {"StrikeNo": 5, "BallPosition": "FL", "StrikePosition": "F", "StrikeTech": "Block", "GameAction": "Defensive", "StrikeEffect": "L4", "SpinKind": "NT", "HitPlayer": "10"}, {"StrikeNo": 6, "BallPosition": "BL", "StrikePosition": "B", "StrikeTech": "Topspin", "GameAction": "Offensive", "StrikeEffect": "L1", "SpinKind": "NT", "HitPlayer": "00"}, {"StrikeNo": 7, "BallPosition": "BL", "StrikePosition": "B", "StrikeTech": "Attack", "GameAction": "Stalemate", "StrikeEffect": "L5", "SpinKind": "SK", "HitPlayer": "10"}]}, {"RallyNo": 12, "startTime": 1846.4339317, "endTime": 1855.2532742, "startSide": 1, "winSide": 1, "score": [6, 5], "list": [{"StrikeNo": 1, "BallPosition": "S1", "StrikePosition": "S1", "StrikeTech": "Reverse", "GameAction": "Serve", "StrikeEffect": "L4", "SpinKind": "NT", "HitPlayer": "10"}, {"StrikeNo": 2, "BallPosition": "MS", "StrikePosition": "B", "StrikeTech": "Twist", "GameAction": "Receive", "StrikeEffect": "L3", "SpinKind": "NT", "HitPlayer": "00"}, {"StrikeNo": 3, "BallPosition": "BL", "StrikePosition": "B", "StrikeTech": "Attack", "GameAction": "Stalemate", "StrikeEffect": "L3", "SpinKind": "SK", "HitPlayer": "10"}, {"StrikeNo": 4, "BallPosition": "BL", "StrikePosition": "B", "StrikeTech": "Topspin", "GameAction": "Stalemate", "StrikeEffect": "L3", "SpinKind": "NT", "HitPlayer": "00"}, {"StrikeNo": 5, "BallPosition": "BL", "StrikePosition": "B", "StrikeTech": "Attack", "GameAction": "Stalemate", "StrikeEffect": "L3", "SpinKind": "SK", "HitPlayer": "10"}, {"StrikeNo": 6, "BallPosition": "BL", "StrikePosition": "B", "StrikeTech": "Topspin", "GameAction": "Stalemate", "StrikeEffect": "L3", "SpinKind": "NT", "HitPlayer": "00"}, {"StrikeNo": 7, "BallPosition": "BL", "StrikePosition": "B", "StrikeTech": "Attack", "GameAction": "Stalemate", "StrikeEffect": "L1", "SpinKind": "SK", "HitPlayer": "10"}, {"StrikeNo": 8, "BallPosition": "ML", "StrikePosition": "B", "StrikeTech": "Topspin", "GameAction": "Stalemate", "StrikeEffect": "L5", "SpinKind": "NT", "HitPlayer": "00"}]}, {"RallyNo": 13, "startTime": 1878.0024625, "endTime": 1884.9935965, "startSide": 0, "winSide": 0, "score": [6, 6], "list": [{"StrikeNo": 1, "BallPosition": "S1", "StrikePosition": "S1", "StrikeTech": "Pendulum", "GameAction": "Serve", "StrikeEffect": "L1", "SpinKind": "NT", "HitPlayer": "00"}, {"StrikeNo": 2, "BallPosition": "ML", "StrikePosition": "B", "StrikeTech": "Attack", "GameAction": "Receive", "StrikeEffect": "L5", "SpinKind": "SK", "HitPlayer": "10"}]}, {"RallyNo": 14, "startTime": 1896.3705552, "endTime": 1903.5040356, "startSide": 0, "winSide": 1, "score": [7, 6], "list": [{"StrikeNo": 1, "BallPosition": "S1", "StrikePosition": "S1", "StrikeTech": "Pendulum", "GameAction": "Serve", "StrikeEffect": "L4", "SpinKind": "NT", "HitPlayer": "00"}, {"StrikeNo": 2, "BallPosition": "ML", "StrikePosition": "B", "StrikeTech": "Attack", "GameAction": "Receive", "StrikeEffect": "L1", "SpinKind": "SK", "HitPlayer": "10"}, {"StrikeNo": 3, "BallPosition": "BL", "StrikePosition": "B", "StrikeTech": "Topspin", "GameAction": "Stalemate", "StrikeEffect": "L5", "SpinKind": "NT", "HitPlayer": "00"}]}, {"RallyNo": 15, "startTime": 1918.489544, "endTime": 1924.6071361, "startSide": 1, "winSide": 1, "score": [7, 7], "list": [{"StrikeNo": 1, "BallPosition": "S2", "StrikePosition": "S2", "StrikeTech": "Reverse", "GameAction": "Serve", "StrikeEffect": "L1", "SpinKind": "ND", "HitPlayer": "10"}, {"StrikeNo": 2, "BallPosition": "BS", "StrikePosition": "B", "StrikeTech": "Twist", "GameAction": "Receive", "StrikeEffect": "L5", "SpinKind": "NT", "HitPlayer": "00"}]}, {"RallyNo": 16, "startTime": 1935.7352411, "endTime": 1942.8484714, "startSide": 1, "winSide": 1, "score": [7, 8], "list": [{"StrikeNo": 1, "BallPosition": "S2", "StrikePosition": "S2", "StrikeTech": "Reverse", "GameAction": "Serve", "StrikeEffect": "L2", "SpinKind": "ND", "HitPlayer": "10"}, {"StrikeNo": 2, "BallPosition": "FS", "StrikePosition": "F", "StrikeTech": "Push", "GameAction": "Receive", "StrikeEffect": "L4", "SpinKind": "ND", "HitPlayer": "00"}, {"StrikeNo": 3, "BallPosition": "BL", "StrikePosition": "B", "StrikeTech": "Topspin", "GameAction": "Offensive", "StrikeEffect": "L1", "SpinKind": "ST", "HitPlayer": "10"}, {"StrikeNo": 4, "BallPosition": "BL", "StrikePosition": "B", "StrikeTech": "Topspin", "GameAction": "Stalemate", "StrikeEffect": "L5", "SpinKind": "NT", "HitPlayer": "00"}]}, {"RallyNo": 17, "startTime": 1954.7038261, "endTime": 1963.6445021, "startSide": 0, "winSide": 0, "score": [7, 9], "list": [{"StrikeNo": 1, "BallPosition": "S1", "StrikePosition": "S1", "StrikeTech": "Pendulum", "GameAction": "Serve", "StrikeEffect": "L3", "SpinKind": "ND", "HitPlayer": "00"}, {"StrikeNo": 2, "BallPosition": "BS", "StrikePosition": "B", "StrikeTech": "Short", "GameAction": "Receive", "StrikeEffect": "L3", "SpinKind": "ND", "HitPlayer": "10"}, {"StrikeNo": 3, "BallPosition": "BS", "StrikePosition": "B", "StrikeTech": "Push", "GameAction": "Controlled", "StrikeEffect": "L4", "SpinKind": "ND", "HitPlayer": "00"}, {"StrikeNo": 4, "BallPosition": "BL", "StrikePosition": "P", "StrikeTech": "Topspin", "GameAction": "Offensive", "StrikeEffect": "L2", "SpinKind": "ST", "HitPlayer": "10"}, {"StrikeNo": 5, "BallPosition": "BL", "StrikePosition": "B", "StrikeTech": "Block", "GameAction": "Defensive", "StrikeEffect": "L1", "SpinKind": "NT", "HitPlayer": "00"}, {"StrikeNo": 6, "BallPosition": "FL", "StrikePosition": "F", "StrikeTech": "Topspin", "GameAction": "Offensive", "StrikeEffect": "L5", "SpinKind": "WT", "HitPlayer": "10"}]}, {"RallyNo": 18, "startTime": 1979.3216692, "endTime": 1986.9885454, "startSide": 0, "winSide": 0, "score": [8, 9], "list": [{"StrikeNo": 1, "BallPosition": "S1", "StrikePosition": "S1", "StrikeTech": "Pendulum", "GameAction": "Serve", "StrikeEffect": "L4", "SpinKind": "NT", "HitPlayer": "00"}, {"StrikeNo": 2, "BallPosition": "BL", "StrikePosition": "B", "StrikeTech": "Attack", "GameAction": "Receive", "StrikeEffect": "L3", "SpinKind": "SK", "HitPlayer": "10"}, {"StrikeNo": 3, "BallPosition": "BL", "StrikePosition": "B", "StrikeTech": "Topspin", "GameAction": "Stalemate", "StrikeEffect": "L1", "SpinKind": "NT", "HitPlayer": "00"}, {"StrikeNo": 4, "BallPosition": "BL", "StrikePosition": "B", "StrikeTech": "Attack", "GameAction": "Stalemate", "StrikeEffect": "L5", "SpinKind": "SK", "HitPlayer": "10"}]}, {"RallyNo": 19, "startTime": 2009.1217337, "endTime": 2016.5438391, "startSide": 1, "winSide": 1, "score": [9, 9], "list": [{"StrikeNo": 1, "BallPosition": "S2", "StrikePosition": "S2", "StrikeTech": "Reverse", "GameAction": "Serve", "StrikeEffect": "L2", "SpinKind": "ND", "HitPlayer": "10"}, {"StrikeNo": 2, "BallPosition": "FS", "StrikePosition": "T", "StrikeTech": "Push", "GameAction": "Receive", "StrikeEffect": "L4", "SpinKind": "ND", "HitPlayer": "00"}, {"StrikeNo": 3, "BallPosition": "BL", "StrikePosition": "B", "StrikeTech": "Topspin", "GameAction": "Offensive", "StrikeEffect": "L1", "SpinKind": "ST", "HitPlayer": "10"}, {"StrikeNo": 4, "BallPosition": "BL", "StrikePosition": "B", "StrikeTech": "Topspin", "GameAction": "Stalemate", "StrikeEffect": "L5", "SpinKind": "NT", "HitPlayer": "00"}]}, {"RallyNo": 20, "startTime": 2028.9486729, "endTime": 2035.1765281, "startSide": 1, "winSide": 0, "score": [9, 10], "list": [{"StrikeNo": 1, "BallPosition": "S2", "StrikePosition": "S2", "StrikeTech": "Reverse", "GameAction": "Serve", "StrikeEffect": "L2", "SpinKind": "ND", "HitPlayer": "10"}, {"StrikeNo": 2, "BallPosition": "FS", "StrikePosition": "F", "StrikeTech": "Push", "GameAction": "Receive", "StrikeEffect": "L1", "SpinKind": "ND", "HitPlayer": "00"}, {"StrikeNo": 3, "BallPosition": "BL", "StrikePosition": "P", "StrikeTech": "Topspin", "GameAction": "Offensive", "StrikeEffect": "L5", "SpinKind": "ST", "HitPlayer": "10"}]}, {"RallyNo": 21, "startTime": 2056.6693202, "endTime": 2064.3480376, "startSide": 0, "winSide": 1, "score": [10, 10], "list": [{"StrikeNo": 1, "BallPosition": "S1", "StrikePosition": "S1", "StrikeTech": "Pendulum", "GameAction": "Serve", "StrikeEffect": "L4", "SpinKind": "NT", "HitPlayer": "00"}, {"StrikeNo": 2, "BallPosition": "BL", "StrikePosition": "B", "StrikeTech": "Topspin", "GameAction": "Receive", "StrikeEffect": "L3", "SpinKind": "NT", "HitPlayer": "10"}, {"StrikeNo": 3, "BallPosition": "BL", "StrikePosition": "B", "StrikeTech": "Topspin", "GameAction": "Stalemate", "StrikeEffect": "L3", "SpinKind": "NT", "HitPlayer": "00"}, {"StrikeNo": 4, "BallPosition": "BL", "StrikePosition": "B", "StrikeTech": "Attack", "GameAction": "Stalemate", "StrikeEffect": "L3", "SpinKind": "SK", "HitPlayer": "10"}, {"StrikeNo": 5, "BallPosition": "ML", "StrikePosition": "P", "StrikeTech": "Topspin", "GameAction": "Stalemate", "StrikeEffect": "L3", "SpinKind": "NT", "HitPlayer": "00"}, {"StrikeNo": 6, "BallPosition": "FL", "StrikePosition": "F", "StrikeTech": "Topspin", "GameAction": "Stalemate", "StrikeEffect": "L1", "SpinKind": "NT", "HitPlayer": "10"}, {"StrikeNo": 7, "BallPosition": "BL", "StrikePosition": "B", "StrikeTech": "Block", "GameAction": "Defensive", "StrikeEffect": "L5", "SpinKind": "NT", "HitPlayer": "00"}]}, {"RallyNo": 22, "startTime": 2082.0585381, "endTime": 2089.0681851, "startSide": 1, "winSide": 0, "score": [10, 11], "list": [{"StrikeNo": 1, "BallPosition": "S2", "StrikePosition": "S2", "StrikeTech": "Reverse", "GameAction": "Serve", "StrikeEffect": "L2", "SpinKind": "ND", "HitPlayer": "10"}, {"StrikeNo": 2, "BallPosition": "MS", "StrikePosition": "B", "StrikeTech": "Push", "GameAction": "Receive", "StrikeEffect": "L4", "SpinKind": "ND", "HitPlayer": "00"}, {"StrikeNo": 3, "BallPosition": "BL", "StrikePosition": "B", "StrikeTech": "Topspin", "GameAction": "Offensive", "StrikeEffect": "L3", "SpinKind": "ST", "HitPlayer": "10"}, {"StrikeNo": 4, "BallPosition": "BL", "StrikePosition": "B", "StrikeTech": "Topspin", "GameAction": "Stalemate", "StrikeEffect": "L1", "SpinKind": "NT", "HitPlayer": "00"}, {"StrikeNo": 5, "BallPosition": "BL", "StrikePosition": "B", "StrikeTech": "Block", "GameAction": "Defensive", "StrikeEffect": "L5", "SpinKind": "SK", "HitPlayer": "10"}]}, {"RallyNo": 23, "startTime": 2107.4893732, "endTime": 2114.0256659, "startSide": 0, "winSide": 0, "score": [11, 11], "list": [{"StrikeNo": 1, "BallPosition": "S1", "StrikePosition": "S1", "StrikeTech": "Pendulum", "GameAction": "Serve", "StrikeEffect": "L1", "SpinKind": "NT", "HitPlayer": "00"}, {"StrikeNo": 2, "BallPosition": "ML", "StrikePosition": "B", "StrikeTech": "Attack", "GameAction": "Receive", "StrikeEffect": "L5", "SpinKind": "SK", "HitPlayer": "10"}]}, {"RallyNo": 24, "startTime": 2130.0055624, "endTime": 2137.8147512, "startSide": 1, "winSide": 1, "score": [12, 11], "list": [{"StrikeNo": 1, "BallPosition": "S2", "StrikePosition": "S2", "StrikeTech": "Reverse", "GameAction": "Serve", "StrikeEffect": "L2", "SpinKind": "ND", "HitPlayer": "10"}, {"StrikeNo": 2, "BallPosition": "FS", "StrikePosition": "T", "StrikeTech": "Push", "GameAction": "Receive", "StrikeEffect": "L4", "SpinKind": "ND", "HitPlayer": "00"}, {"StrikeNo": 3, "BallPosition": "BL", "StrikePosition": "B", "StrikeTech": "Topspin", "GameAction": "Offensive", "StrikeEffect": "L3", "SpinKind": "ST", "HitPlayer": "10"}, {"StrikeNo": 4, "BallPosition": "FL", "StrikePosition": "F", "StrikeTech": "Topspin", "GameAction": "Stalemate", "StrikeEffect": "L2", "SpinKind": "NT", "HitPlayer": "00"}, {"StrikeNo": 5, "BallPosition": "FL", "StrikePosition": "F", "StrikeTech": "Block", "GameAction": "Defensive", "StrikeEffect": "L1", "SpinKind": "NT", "HitPlayer": "10"}, {"StrikeNo": 6, "BallPosition": "BL", "StrikePosition": "B", "StrikeTech": "Topspin", "GameAction": "Offensive", "StrikeEffect": "L5", "SpinKind": "NT", "HitPlayer": "00"}]}, {"RallyNo": 25, "startTime": 2164.6544395, "endTime": 2170.969753, "startSide": 0, "winSide": 1, "score": [12, 12], "list": [{"StrikeNo": 1, "BallPosition": "S1", "StrikePosition": "S1", "StrikeTech": "Pendulum", "GameAction": "Serve", "StrikeEffect": "L4", "SpinKind": "NT", "HitPlayer": "00"}, {"StrikeNo": 2, "BallPosition": "BL", "StrikePosition": "B", "StrikeTech": "Attack", "GameAction": "Receive", "StrikeEffect": "L1", "SpinKind": "SK", "HitPlayer": "10"}, {"StrikeNo": 3, "BallPosition": "BL", "StrikePosition": "B", "StrikeTech": "Topspin", "GameAction": "Stalemate", "StrikeEffect": "L5", "SpinKind": "NT", "HitPlayer": "00"}]}, {"RallyNo": 26, "startTime": 2182.7174408, "endTime": 2187.441004, "startSide": 1, "winSide": 0, "score": [12, 13], "list": [{"StrikeNo": 1, "BallPosition": "S2", "StrikePosition": "S2", "StrikeTech": "Reverse", "GameAction": "Serve", "StrikeEffect": "L4", "SpinKind": "NT", "HitPlayer": "10"}, {"StrikeNo": 2, "BallPosition": "ML", "StrikePosition": "P", "StrikeTech": "Topspin", "GameAction": "Receive", "StrikeEffect": "L1", "SpinKind": "NT", "HitPlayer": "00"}, {"StrikeNo": 3, "BallPosition": "FL", "StrikePosition": "F", "StrikeTech": "Attack", "GameAction": "Stalemate", "StrikeEffect": "L5", "SpinKind": "NT", "HitPlayer": "10"}]}, {"RallyNo": 27, "startTime": 2223.095297, "endTime": 2235.0799031, "startSide": 0, "winSide": 1, "score": [13, 13], "list": [{"StrikeNo": 1, "BallPosition": "S2", "StrikePosition": "S2", "StrikeTech": "Pendulum", "GameAction": "Serve", "StrikeEffect": "L3", "SpinKind": "ND", "HitPlayer": "00"}, {"StrikeNo": 2, "BallPosition": "FS", "StrikePosition": "T", "StrikeTech": "Short", "GameAction": "Receive", "StrikeEffect": "L3", "SpinKind": "ND", "HitPlayer": "10"}, {"StrikeNo": 3, "BallPosition": "FS", "StrikePosition": "F", "StrikeTech": "Push", "GameAction": "Controlled", "StrikeEffect": "L4", "SpinKind": "ND", "HitPlayer": "00"}, {"StrikeNo": 4, "BallPosition": "FL", "StrikePosition": "F", "StrikeTech": "Topspin", "GameAction": "Offensive", "StrikeEffect": "L3", "SpinKind": "ST", "HitPlayer": "10"}, {"StrikeNo": 5, "BallPosition": "ML", "StrikePosition": "T", "StrikeTech": "Topspin", "GameAction": "Stalemate", "StrikeEffect": "L2", "SpinKind": "NT", "HitPlayer": "00"}, {"StrikeNo": 6, "BallPosition": "BL", "StrikePosition": "B", "StrikeTech": "Block", "GameAction": "Defensive", "StrikeEffect": "L4", "SpinKind": "SK", "HitPlayer": "10"}, {"StrikeNo": 7, "BallPosition": "BL", "StrikePosition": "B", "StrikeTech": "Topspin", "GameAction": "Offensive", "StrikeEffect": "L3", "SpinKind": "NT", "HitPlayer": "00"}, {"StrikeNo": 8, "BallPosition": "BL", "StrikePosition": "B", "StrikeTech": "Attack", "GameAction": "Stalemate", "StrikeEffect": "L3", "SpinKind": "SK", "HitPlayer": "10"}, {"StrikeNo": 9, "BallPosition": "ML", "StrikePosition": "P", "StrikeTech": "Topspin", "GameAction": "Stalemate", "StrikeEffect": "L2", "SpinKind": "NT", "HitPlayer": "00"}, {"StrikeNo": 10, "BallPosition": "BL", "StrikePosition": "B", "StrikeTech": "Block", "GameAction": "Defensive", "StrikeEffect": "L4", "SpinKind": "SK", "HitPlayer": "10"}, {"StrikeNo": 11, "BallPosition": "SP", "StrikePosition": "F", "StrikeTech": "Topspin", "GameAction": "Offensive", "StrikeEffect": "L3", "SpinKind": "NT", "HitPlayer": "00"}, {"StrikeNo": 12, "BallPosition": "FL", "StrikePosition": "F", "StrikeTech": "Topspin", "GameAction": "Stalemate", "StrikeEffect": "L1", "SpinKind": "NT", "HitPlayer": "10"}, {"StrikeNo": 13, "BallPosition": "BL", "StrikePosition": "B", "StrikeTech": "Topspin", "GameAction": "Stalemate", "StrikeEffect": "L5", "SpinKind": "NT", "HitPlayer": "00"}]}, {"RallyNo": 28, "startTime": 2257.1626745, "endTime": 2264.4528215, "startSide": 1, "winSide": 1, "score": [13, 14], "list": [{"StrikeNo": 1, "BallPosition": "S2", "StrikePosition": "S2", "StrikeTech": "Reverse", "GameAction": "Serve", "StrikeEffect": "L2", "SpinKind": "ND", "HitPlayer": "10"}, {"StrikeNo": 2, "BallPosition": "FS", "StrikePosition": "T", "StrikeTech": "Push", "GameAction": "Receive", "StrikeEffect": "L4", "SpinKind": "ND", "HitPlayer": "00"}, {"StrikeNo": 3, "BallPosition": "BL", "StrikePosition": "P", "StrikeTech": "Topspin", "GameAction": "Offensive", "StrikeEffect": "L1", "SpinKind": "ST", "HitPlayer": "10"}, {"StrikeNo": 4, "BallPosition": "FL", "StrikePosition": "F", "StrikeTech": "Topspin", "GameAction": "Stalemate", "StrikeEffect": "L5", "SpinKind": "NT", "HitPlayer": "00"}]}]}, {"GameNo": 5, "result": [11, 2], "score": [3, 1], "list": [{"RallyNo": 1, "startTime": 2368.0086091, "endTime": 2374.4305347, "startSide": 1, "winSide": 0, "score": [0, 0], "list": [{"StrikeNo": 1, "BallPosition": "S2", "StrikePosition": "S2", "StrikeTech": "Reverse", "GameAction": "Serve", "StrikeEffect": "L2", "SpinKind": "ND", "HitPlayer": "10"}, {"StrikeNo": 2, "BallPosition": "FS", "StrikePosition": "F", "StrikeTech": "Push", "GameAction": "Receive", "StrikeEffect": "L1", "SpinKind": "ND", "HitPlayer": "00"}, {"StrikeNo": 3, "BallPosition": "BL", "StrikePosition": "B", "StrikeTech": "Topspin", "GameAction": "Offensive", "StrikeEffect": "L5", "SpinKind": "ST", "HitPlayer": "10"}]}, {"RallyNo": 2, "startTime": 2383.1190559, "endTime": 2392.9053908, "startSide": 1, "winSide": 0, "score": [1, 0], "list": [{"StrikeNo": 1, "BallPosition": "S2", "StrikePosition": "S2", "StrikeTech": "Reverse", "GameAction": "Serve", "StrikeEffect": "L4", "SpinKind": "NT", "HitPlayer": "10"}, {"StrikeNo": 2, "BallPosition": "BL", "StrikePosition": "B", "StrikeTech": "Topspin", "GameAction": "Receive", "StrikeEffect": "L3", "SpinKind": "NT", "HitPlayer": "00"}, {"StrikeNo": 3, "BallPosition": "ML", "StrikePosition": "B", "StrikeTech": "Attack", "GameAction": "Stalemate", "StrikeEffect": "L3", "SpinKind": "SK", "HitPlayer": "10"}, {"StrikeNo": 4, "BallPosition": "FL", "StrikePosition": "F", "StrikeTech": "Topspin", "GameAction": "Stalemate", "StrikeEffect": "L2", "SpinKind": "NT", "HitPlayer": "00"}, {"StrikeNo": 5, "BallPosition": "FL", "StrikePosition": "F", "StrikeTech": "Block", "GameAction": "Defensive", "StrikeEffect": "L4", "SpinKind": "NT", "HitPlayer": "10"}, {"StrikeNo": 6, "BallPosition": "BL", "StrikePosition": "B", "StrikeTech": "Topspin", "GameAction": "Offensive", "StrikeEffect": "L3", "SpinKind": "NT", "HitPlayer": "00"}, {"StrikeNo": 7, "BallPosition": "BL", "StrikePosition": "B", "StrikeTech": "Attack", "GameAction": "Stalemate", "StrikeEffect": "L3", "SpinKind": "SK", "HitPlayer": "10"}, {"StrikeNo": 8, "BallPosition": "BL", "StrikePosition": "B", "StrikeTech": "Topspin", "GameAction": "Stalemate", "StrikeEffect": "L1", "SpinKind": "NT", "HitPlayer": "00"}, {"StrikeNo": 9, "BallPosition": "BL", "StrikePosition": "B", "StrikeTech": "Attack", "GameAction": "Stalemate", "StrikeEffect": "L5", "SpinKind": "SK", "HitPlayer": "10"}]}, {"RallyNo": 3, "startTime": 2406.9081415, "endTime": 2413.7910672, "startSide": 0, "winSide": 0, "score": [2, 0], "list": [{"StrikeNo": 1, "BallPosition": "S1", "StrikePosition": "S1", "StrikeTech": "Pendulum", "GameAction": "Serve", "StrikeEffect": "L4", "SpinKind": "NT", "HitPlayer": "00"}, {"StrikeNo": 2, "BallPosition": "MH", "StrikePosition": "B", "StrikeTech": "Flick", "GameAction": "Receive", "StrikeEffect": "L3", "SpinKind": "SK", "HitPlayer": "10"}, {"StrikeNo": 3, "BallPosition": "FL", "StrikePosition": "F", "StrikeTech": "Topspin", "GameAction": "Stalemate", "StrikeEffect": "L1", "SpinKind": "NT", "HitPlayer": "00"}, {"StrikeNo": 4, "BallPosition": "FL", "StrikePosition": "F", "StrikeTech": "Topspin", "GameAction": "Stalemate", "StrikeEffect": "L5", "SpinKind": "NT", "HitPlayer": "10"}]}, {"RallyNo": 4, "startTime": 2426.6865757, "endTime": 2433.1365768, "startSide": 0, "winSide": 0, "score": [3, 0], "list": [{"StrikeNo": 1, "BallPosition": "S1", "StrikePosition": "S1", "StrikeTech": "Pendulum", "GameAction": "Serve", "StrikeEffect": "L1", "SpinKind": "ND", "HitPlayer": "00"}, {"StrikeNo": 2, "BallPosition": "MS", "StrikePosition": "B", "StrikeTech": "Flick", "GameAction": "Receive", "StrikeEffect": "L5", "SpinKind": "SK", "HitPlayer": "10"}]}, {"RallyNo": 5, "startTime": 2444.6173065, "endTime": 2451.2260237, "startSide": 1, "winSide": 1, "score": [4, 0], "list": [{"StrikeNo": 1, "BallPosition": "S1", "StrikePosition": "S1", "StrikeTech": "Reverse", "GameAction": "Serve", "StrikeEffect": "L2", "SpinKind": "ND", "HitPlayer": "10"}, {"StrikeNo": 2, "BallPosition": "BH", "StrikePosition": "B", "StrikeTech": "Push", "GameAction": "Receive", "StrikeEffect": "L4", "SpinKind": "ND", "HitPlayer": "00"}, {"StrikeNo": 3, "BallPosition": "BL", "StrikePosition": "B", "StrikeTech": "Topspin", "GameAction": "Offensive", "StrikeEffect": "L1", "SpinKind": "ST", "HitPlayer": "10"}, {"StrikeNo": 4, "BallPosition": "ML", "StrikePosition": "F", "StrikeTech": "Topspin", "GameAction": "Stalemate", "StrikeEffect": "L5", "SpinKind": "NT", "HitPlayer": "00"}]}, {"RallyNo": 6, "startTime": 2468.1720954, "endTime": 2479.5743681, "startSide": 1, "winSide": 0, "score": [4, 1], "list": [{"StrikeNo": 1, "BallPosition": "S1", "StrikePosition": "S1", "StrikeTech": "Reverse", "GameAction": "Serve", "StrikeEffect": "L4", "SpinKind": "NT", "HitPlayer": "10"}, {"StrikeNo": 2, "BallPosition": "BL", "StrikePosition": "B", "StrikeTech": "Topspin", "GameAction": "Receive", "StrikeEffect": "L3", "SpinKind": "NT", "HitPlayer": "00"}, {"StrikeNo": 3, "BallPosition": "FL", "StrikePosition": "F", "StrikeTech": "Attack", "GameAction": "Stalemate", "StrikeEffect": "L2", "SpinKind": "NT", "HitPlayer": "10"}, {"StrikeNo": 4, "BallPosition": "FL", "StrikePosition": "F", "StrikeTech": "Block", "GameAction": "Defensive", "StrikeEffect": "L2", "SpinKind": "NT", "HitPlayer": "00"}, {"StrikeNo": 5, "BallPosition": "BL", "StrikePosition": "B", "StrikeTech": "Others", "GameAction": "Defensive", "StrikeEffect": "L4", "SpinKind": "NT", "HitPlayer": "10"}, {"StrikeNo": 6, "BallPosition": "BL", "StrikePosition": "B", "StrikeTech": "Topspin", "GameAction": "Offensive", "StrikeEffect": "L3", "SpinKind": "ST", "HitPlayer": "00"}, {"StrikeNo": 7, "BallPosition": "BL", "StrikePosition": "B", "StrikeTech": "Attack", "GameAction": "Stalemate", "StrikeEffect": "L3", "SpinKind": "SK", "HitPlayer": "10"}, {"StrikeNo": 8, "BallPosition": "BL", "StrikePosition": "B", "StrikeTech": "Topspin", "GameAction": "Stalemate", "StrikeEffect": "L3", "SpinKind": "NT", "HitPlayer": "00"}, {"StrikeNo": 9, "BallPosition": "BL", "StrikePosition": "B", "StrikeTech": "Attack", "GameAction": "Stalemate", "StrikeEffect": "L3", "SpinKind": "SK", "HitPlayer": "10"}, {"StrikeNo": 10, "BallPosition": "BL", "StrikePosition": "B", "StrikeTech": "Topspin", "GameAction": "Stalemate", "StrikeEffect": "L2", "SpinKind": "NT", "HitPlayer": "00"}, {"StrikeNo": 11, "BallPosition": "ML", "StrikePosition": "B", "StrikeTech": "Block", "GameAction": "Defensive", "StrikeEffect": "L4", "SpinKind": "SK", "HitPlayer": "10"}, {"StrikeNo": 12, "BallPosition": "ML", "StrikePosition": "F", "StrikeTech": "Topspin", "GameAction": "Offensive", "StrikeEffect": "L1", "SpinKind": "NT", "HitPlayer": "00"}, {"StrikeNo": 13, "BallPosition": "FL", "StrikePosition": "F", "StrikeTech": "Block", "GameAction": "Defensive", "StrikeEffect": "L5", "SpinKind": "NT", "HitPlayer": "10"}]}, {"RallyNo": 7, "startTime": 2505.2636892, "endTime": 2513.7115943, "startSide": 0, "winSide": 0, "score": [5, 1], "list": [{"StrikeNo": 1, "BallPosition": "S1", "StrikePosition": "S1", "StrikeTech": "Pendulum", "GameAction": "Serve", "StrikeEffect": "L1", "SpinKind": "NT", "HitPlayer": "00"}, {"StrikeNo": 2, "BallPosition": "BH", "StrikePosition": "B", "StrikeTech": "Twist", "GameAction": "Receive", "StrikeEffect": "L5", "SpinKind": "SK", "HitPlayer": "10"}]}, {"RallyNo": 8, "startTime": 2522.7360321, "endTime": 2530.0006583, "startSide": 0, "winSide": 1, "score": [6, 1], "list": [{"StrikeNo": 1, "BallPosition": "S1", "StrikePosition": "S1", "StrikeTech": "Pendulum", "GameAction": "Serve", "StrikeEffect": "L4", "SpinKind": "NT", "HitPlayer": "00"}, {"StrikeNo": 2, "BallPosition": "BS", "StrikePosition": "B", "StrikeTech": "Flick", "GameAction": "Receive", "StrikeEffect": "L1", "SpinKind": "SK", "HitPlayer": "10"}, {"StrikeNo": 3, "BallPosition": "FL", "StrikePosition": "F", "StrikeTech": "Block", "GameAction": "Defensive", "StrikeEffect": "L5", "SpinKind": "NT", "HitPlayer": "00"}]}, {"RallyNo": 9, "startTime": 2542.2323047, "endTime": 2549.3648345, "startSide": 1, "winSide": 0, "score": [6, 2], "list": [{"StrikeNo": 1, "BallPosition": "S2", "StrikePosition": "S2", "StrikeTech": "Reverse", "GameAction": "Serve", "StrikeEffect": "L3", "SpinKind": "ND", "HitPlayer": "10"}, {"StrikeNo": 2, "BallPosition": "FS", "StrikePosition": "F", "StrikeTech": "Short", "GameAction": "Receive", "StrikeEffect": "L3", "SpinKind": "ND", "HitPlayer": "00"}, {"StrikeNo": 3, "BallPosition": "FS", "StrikePosition": "F", "StrikeTech": "Short", "GameAction": "Controlled", "StrikeEffect": "L4", "SpinKind": "ND", "HitPlayer": "10"}, {"StrikeNo": 4, "BallPosition": "FH", "StrikePosition": "F", "StrikeTech": "Topspin", "GameAction": "Offensive", "StrikeEffect": "L1", "SpinKind": "ST", "HitPlayer": "00"}, {"StrikeNo": 5, "BallPosition": "FL", "StrikePosition": "F", "StrikeTech": "Block", "GameAction": "Defensive", "StrikeEffect": "L5", "SpinKind": "NT", "HitPlayer": "10"}]}, {"RallyNo": 10, "startTime": 2562.2597308, "endTime": 2569.4277112, "startSide": 1, "winSide": 0, "score": [7, 2], "list": [{"StrikeNo": 1, "BallPosition": "S2", "StrikePosition": "S2", "StrikeTech": "Reverse", "GameAction": "Serve", "StrikeEffect": "L2", "SpinKind": "NT", "HitPlayer": "10"}, {"StrikeNo": 2, "BallPosition": "BH", "StrikePosition": "B", "StrikeTech": "Push", "GameAction": "Receive", "StrikeEffect": "L1", "SpinKind": "ND", "HitPlayer": "00"}, {"StrikeNo": 3, "BallPosition": "BL", "StrikePosition": "B", "StrikeTech": "Attack", "GameAction": "Offensive", "StrikeEffect": "L5", "SpinKind": "SK", "HitPlayer": "10"}]}, {"RallyNo": 11, "startTime": 2579.7726701, "endTime": 2586.0080331, "startSide": 0, "winSide": 0, "score": [8, 2], "list": [{"StrikeNo": 1, "BallPosition": "S1", "StrikePosition": "S1", "StrikeTech": "Pendulum", "GameAction": "Serve", "StrikeEffect": "L4", "SpinKind": "NT", "HitPlayer": "00"}, {"StrikeNo": 2, "BallPosition": "ML", "StrikePosition": "P", "StrikeTech": "Topspin", "GameAction": "Receive", "StrikeEffect": "L2", "SpinKind": "NT", "HitPlayer": "10"}, {"StrikeNo": 3, "BallPosition": "BL", "StrikePosition": "B", "StrikeTech": "Block", "GameAction": "Defensive", "StrikeEffect": "L1", "SpinKind": "NT", "HitPlayer": "00"}, {"StrikeNo": 4, "BallPosition": "FL", "StrikePosition": "F", "StrikeTech": "Others", "GameAction": "Stalemate", "StrikeEffect": "L5", "SpinKind": "WT", "HitPlayer": "10"}]}, {"RallyNo": 12, "startTime": 2598.6938254, "endTime": 2605.4839802, "startSide": 0, "winSide": 0, "score": [9, 2], "list": [{"StrikeNo": 1, "BallPosition": "S1", "StrikePosition": "S1", "StrikeTech": "Pendulum", "GameAction": "Serve", "StrikeEffect": "L3", "SpinKind": "ND", "HitPlayer": "00"}, {"StrikeNo": 2, "BallPosition": "BS", "StrikePosition": "B", "StrikeTech": "Others", "GameAction": "Receive", "StrikeEffect": "L3", "SpinKind": "ND", "HitPlayer": "10"}, {"StrikeNo": 3, "BallPosition": "BL", "StrikePosition": "B", "StrikeTech": "Push", "GameAction": "Controlled", "StrikeEffect": "L1", "SpinKind": "ND", "HitPlayer": "00"}, {"StrikeNo": 4, "BallPosition": "BL", "StrikePosition": "B", "StrikeTech": "Attack", "GameAction": "Offensive", "StrikeEffect": "L5", "SpinKind": "SK", "HitPlayer": "10"}]}, {"RallyNo": 13, "startTime": 2612.2910225, "endTime": 2619.085719, "startSide": 1, "winSide": 0, "score": [10, 2], "list": [{"StrikeNo": 1, "BallPosition": "S1", "StrikePosition": "S1", "StrikeTech": "Pendulum", "GameAction": "Serve", "StrikeEffect": "L4", "SpinKind": "NT", "HitPlayer": "10"}, {"StrikeNo": 2, "BallPosition": "MH", "StrikePosition": "B", "StrikeTech": "Twist", "GameAction": "Receive", "StrikeEffect": "L3", "SpinKind": "NT", "HitPlayer": "00"}, {"StrikeNo": 3, "BallPosition": "BL", "StrikePosition": "B", "StrikeTech": "Attack", "GameAction": "Stalemate", "StrikeEffect": "L3", "SpinKind": "SK", "HitPlayer": "10"}, {"StrikeNo": 4, "BallPosition": "BL", "StrikePosition": "B", "StrikeTech": "Topspin", "GameAction": "Stalemate", "StrikeEffect": "L1", "SpinKind": "NT", "HitPlayer": "00"}, {"StrikeNo": 5, "BallPosition": "BL", "StrikePosition": "B", "StrikeTech": "Attack", "GameAction": "Stalemate", "StrikeEffect": "L5", "SpinKind": "SK", "HitPlayer": "10"}]}]}]}}